{
  "sections": {
    "main": {
      "type": "main-page",
      "disabled": true,
      "settings": {
        "narrow": false,
        "padding_top": 60,
        "padding_bottom": 60
      }
    },
    "a893289b-2595-43c4-bf57-ba711b1e94bc": {
      "type": "image-banner",
      "settings": {
        "image": "shopify:\/\/shop_images\/howtomain.png",
        "image_position": "center center",
        "text_box_position": "bottom-center",
        "text_alignment": "center",
        "image_ratio": "adapt",
        "show_text_box": false,
        "full_width": true,
        "show_divider": false,
        "mobile_text_alignment": "center",
        "mobile_image_ratio": "auto",
        "stack_images_on_mobile": true,
        "show_text_below": true,
        "colors_text": "#ffffff",
        "colors_overlay": "#000000",
        "colors_overlay_opacity": 0,
        "padding_top": 0,
        "padding_bottom": 0
      }
    },
    "8285edb0-3d58-461d-abbe-39af17159741": {
      "type": "custom-liquid",
      "settings": {
        "custom_liquid": "<meta\n  name=\"roseracea-text\"\n  content=\"width=device-width, initial-scale=1, maximum-scale=1, user-scalable=no\"\n\/>\n<style>\n  body {\n    margin: unset;\n  }\n  .container {\n    margin-top: 15px;\n  }\n  .read-more-state {\n    display: none;\n  }\n  .read-more-wrap {\n    margin: 0;\n    font-size: calc(0.75em + 1.15vw);\n  }\n   .read-more-target {\n    opacity: 0;\n    max-height: 0;\n    font-size: 0;\n    transition: 0.25s ease;\n  }\n   .read-more-state:checked ~ .read-more-target {\n    opacity: 1;\n    font-size: calc(0.5em + 1.15vw);;\n    max-height: 999em;\n  }\n  .read-more-state ~ .read-more-trigger:before {\n    content: \"View more\";\n  }\n  .read-more-state:checked ~ .read-more-trigger:before {\n    content: \"View less\";\n  }\n  .read-more-trigger {\n    font-weight: bold;\n    cursor: pointer;\n    display: inline-block;\n    font-size: 0.9em;\n    text-decoration: underline;\n  }\n.parent {\n    background-position: center center;\n    background-repeat: no-repeat;\n    background-size: cover;\n    position: relative;\n    height: 100%;\n    display: grid;\n    place-items: center;\n}\n  .child-head h1 p {\n    font-size: calc(0.4em + 0.35vw);\n    line-height: 0.05vw;\n  }\n  .child-head {\n    font-size: calc(0.3em + 0.35vw);\n    margin-top: -4%;\n  }\n  .final-line {\n    font-size: calc(0.75em + 0.25vw);\n    padding: 0 9vw;\n    margin-bottom: 2%;\n  }\n  .top-line {\n     font-size: 16px;\n     margin: auto;\n     color:#4a4a4a;\n  }\n  .mid-text {\n    display: grid;\n    grid-template-columns: 1fr auto 1fr;\n    align-items: center;\n    grid-gap: 2vw;\n    margin: 0 -3.8%;\n    font-size: calc(0.65em + 0.7vw);\n    font-weight: 400;\n  }\n  .button {\n      padding: 2%;\n      border-radius: 30vw;\n      background: #cc4e61;\n      cursor: pointer;\n  }\n  .mid-text:before,\n  .mid-text:after {\n    content: \"\";\n    display: block;\n    border-top: 2px solid currentColor;\n  }\n  @media (max-width: 767px) {\n    .hidden-mobile {\n      display: none;\n    }\n    .child-head {\n      font-size: calc(0.3em + 1.35vw);\n      margin-top: -6%;\n    }\n    .child-head h1 p {\n      font-size: calc(0.4em + 1.75vw);\n    }\n    .child {\n      width: 80%;\n      bottom: -20%;\n      max-width: 80%;\n    }\n    .read-more-wrap p {\n      line-height: 1.2;\n      font-size: calc(0.50em + 1.00vw);\n      color:#4a4a4a;\n      text-align:center;\n    }\n    .text-2 {\n      line-height: 1.2;\n      color:#4a4a4a;\n      text-align:center;\n    }\n    \n    .read-more-wrap {\n      font-size: calc(0.75em + 1.15vw);\n      color:#4a4a4a;\n    }\n    .final-line {\n      margin-bottom: 2%;\n    }\n    .read-more-trigger {\n      color: #cc4e61;\n      text-align: center;\n    }\n  }\n  @media (min-width: 767px) {\n    .hidden-desktop {\n      display: none;\n    }\n    .button {\n      padding: 1%;\n    }\n  }\n<\/style>\n<div class=\"parent\">\n  <div class=\"child hidden-mobile\">\n    <div class=\"child-head\">\n     <p class=\"top-line\">\n        It can affect your skin, nose, mouth and eyes. Your face may turn red, swell, burn or feel like you're on fire. Rosacea skincare can be tricky and even overwhelming for some, but understanding your condition will not only make it easier to care for but can help identify the triggers that are causing flare-ups.\n<br>\n<br>\nThere seem to be endless skincare options at your fingertips. What works for others may not work for you – and vice versa. For many people who have Rosacea, the trick to managing it is understanding the condition. That's why we are here! Our articles are backed up by scientific research and will help you find your ultimate rosacea skincare routine. Learning how to care for Rosacea properly can help you manage this disease, making it easier to navigate through life.\n<br>\n<br>\nIt is important to note that the information about Rosacea found in this article is supported by scientific research at NCBI.\n      <\/p>\n      <div class=\"read-more-target\">\n        <p class=\"text-2\"> <\/p>\n       <\/div>\n      <\/div>\n  <\/div>\n  <div class=\"child hidden-desktop\">\n     <div class=\"container\" style=\"text-align:center;\">\n      <input\n        type=\"checkbox\"\nstyle=\"display:none\"class=\"read-more-state jcf-hidden\"\n        id=\"following-content\"\n      \/>\n      <div class=\"read-more-wrap\">\n        <p>  It can affect your skin, nose, mouth and eyes. Your face may turn red, swell, burn or feel like you're on fire. Rosacea skincare can be tricky and even overwhelming for some, but understanding your condition will not only make it easier to care for but can help identify the triggers that are causing flare-ups.\n\n<\/p>\n      <\/div>\n        <div class=\"read-more-target\">\n          <p class=\"text-2\">\n\nThere seem to be endless skincare options at your fingertips. What works for others may not work for you – and vice versa. For many people who have Rosacea, the trick to managing it is understanding the condition. That's why we are here! Our articles are backed up by scientific research and will help you find your ultimate rosacea skincare routine. Learning how to care for Rosacea properly can help you manage this disease, making it easier to navigate through life.\n\nIt is important to note that the information about Rosacea found in this article is supported by scientific research at NCBI.<\/p>\n         <\/div>\n\n      <label for=\"following-content\" class=\"read-more-trigger\"><\/label><\/div>\n    <\/div>\n  <\/div>\n<\/div>",
        "full_width": false,
        "show_divider": false,
        "padding_top": 36,
        "columns_mobile": "1",
        "swipe_on_mobile": true,
        "padding_bottom": 36
      }
    },
    "4fc8e1bc-a4dd-40a2-8977-fd97466699e2": {
      "type": "custom-liquid",
      "settings": {
        "custom_liquid": "<style>\n\n\n   .R-line1 {\n           \n        border-radius:10px;\n      display: flex;\n      flex-direction: row;\n      border-radius:10px;\n      justify-content: center;\n      align-items: center;\n      \n      font-size: calc(1.25em + 0.25vmin);\n    }\n@media screen and (max-width:767px){\n.R-line1{\nwidth:100%;\n}\n.R-line1 {\n    border-radius: 10px;\n    display: flex;\n    flex-direction: row;\n    border-radius: 10px;\n    justify-content: center;\n    align-items: center;\n    font-size: calc(2em + -3.75vmin);\n}\n}\n\n.R-line2{\ncolor: #4a4a4a;\n    font-weight: bold;\n    margin: 20px;\n    width: 55%;\n}\n@media screen and (max-width:767px){\n.R-line2{\nwidth:100%;\n}\n.R-line2{\ncolor: #4a4a4a;\n    font-weight: bold;\n    margin: 4px;\n    width: 900%;\n}\n}\n    \n    .R-line1:after {\n      background-color: #cc4e61;\n      border-radius:10px;\n      content: \"\";\n      display: inline-block;\n      height: 2px;\n      \n      \/* vertical-align: middle; *\/\n       width: 100%;\n    }\n \n    .R-line1:after {\n      text-align: center; \nborder-radius:10px;\npadding:0 calc(0.5em + 1.25vmin);\n    }\n@media screen and (max-width:767px){\nwidth:100%;\n .R-line1:after {\n    text-align: center;\n    border-radius: 10px;\n    padding: 0 calc(0em + 9.25vmin);\n}\n}\n\n    \n  <\/style>\n  \n  <div class=\"R-line1\" >\n    <img src=\"https:\/\/cdn.shopify.com\/s\/files\/1\/0669\/6343\/9927\/files\/Group_970.png?v=1668752390\">\n<div class=\"R-line2\" >\n<span >Understanding How to Care for Rosacea Skin<br>\n<\/div>\n<\/a>\n<\/div>\n<\/span>\n<div style=\"font-size:16px;\">The first step in managing your Rosacea is to understand what causes it. The exact cause of Rosacea is still unknown, but it is thought to be genetically mediated. People with Rosacea have higher levels of abnormally processed cathelicidins- these are inflammatory mediators that are part of the skin's defense system.\n<br>\n<br>\nThose who suffer from Rosacea often experience episodes of flushing, burning, stinging or itching in the same area where their rash is located. Similar to acne, this condition can lead to small bumps and pimples on your face. However, it is important to know that these two conditions have some differences.<br>\n<br>\n\nAcne rosacea skincare can be very confusing because both conditions form when pores become clogged with oil and dead skin cells; however, unlike acne, Rosacea occurs when capillaries become enlarged and dilated due to increased blood flow. This leads to redness in the skin which can be blushing or flushing on your cheeks or forehead.\n<\/div>",
        "full_width": false,
        "show_divider": false,
        "padding_top": 36,
        "columns_mobile": "1",
        "swipe_on_mobile": true,
        "padding_bottom": 36
      }
    },
    "00b55c1f-44b3-4f89-a159-d9de3a5b4dc5": {
      "type": "gallery",
      "blocks": {
        "template--17262620999991__00b55c1f-44b3-4f89-a159-d9de3a5b4dc5-16710246244a936951-0": {
          "type": "image",
          "settings": {
            "image": "shopify:\/\/shop_images\/Mask_group_9_2f8b4def-9d86-44da-a4d6-c6acd2867f97.png",
            "image_position": "center center",
            "subheading": "",
            "subheading_size": "h5",
            "heading": "",
            "heading_size": "h3",
            "link": "",
            "text_box_position": "bottom-center"
          }
        },
        "template--17262620999991__00b55c1f-44b3-4f89-a159-d9de3a5b4dc5-16710246244a936951-1": {
          "type": "image",
          "settings": {
            "image": "shopify:\/\/shop_images\/Mask_group_10_81dc56d1-7b73-4bda-88d9-c0875aa1ae74.png",
            "image_position": "center center",
            "subheading": "",
            "subheading_size": "h5",
            "heading": "",
            "heading_size": "h3",
            "link": "",
            "text_box_position": "bottom-center"
          }
        }
      },
      "block_order": [
        "template--17262620999991__00b55c1f-44b3-4f89-a159-d9de3a5b4dc5-16710246244a936951-0",
        "template--17262620999991__00b55c1f-44b3-4f89-a159-d9de3a5b4dc5-16710246244a936951-1"
      ],
      "settings": {
        "per_row": 2,
        "spacing_images": 16,
        "image_height": 340,
        "apply_overlay": false,
        "full_width": true,
        "show_divider": false,
        "heading": "",
        "heading_size": "h1",
        "heading_alignment": "left",
        "heading_tag": "h2",
        "columns_mobile": "1",
        "swipe_on_mobile": true,
        "mobile_image_height": 160,
        "padding_top": 36,
        "padding_bottom": 36
      }
    },
    "018cdaa3-4f46-49ca-9691-71baf263e524": {
      "type": "custom-liquid",
      "settings": {
        "custom_liquid": "<style>\n   .R1-line1 {\n         \n        border-radius:10px;\n      display: flex;\n      flex-direction: row;\n      border-radius:10px;\n      justify-content: center;\n      align-items: center;\n      \n      font-size: calc(1.25em + 0.25vmin);\n    }\n@media screen and (max-width:767px){\n.R1-line1{\nwidth:100%;\n}\n.R1-line1 {\n    border-radius: 10px;\n    display: flex;\n    flex-direction: row;\n    border-radius: 10px;\n    justify-content: center;\n    align-items: center;\n    font-size: calc(2em + -3.75vmin);\n}\n}\n\n.R1-line2{\ncolor: #4a4a4a;\n    font-weight: bold;\n    margin: 20px;\n    width: 55%;\n}\n@media screen and (max-width:767px){\n.R1-line2{\nwidth:100%;\n}\n.R1-line2{\ncolor: #4a4a4a;\n    font-weight: bold;\n    margin: 4px;\n    width: 900%;\n}\n}\n    \n    .R1-line1:after {\n      background-color: #cc4e61;\n      border-radius:10px;\n      content: \"\";\n      display: inline-block;\n      height: 2px;\n      \n      \/* vertical-align: middle; *\/\n       width: 100%;\n    }\n \n    .R1-line1:after {\n      text-align: center; \nborder-radius:10px;\npadding:0 calc(0.5em + 1.25vmin);\n    }\n@media screen and (max-width:767px){\nwidth:100%;\n .R1-line1:after {\n    text-align: center;\n    border-radius: 10px;\n    padding: 0 calc(0em + 9.25vmin);\n}\n}\n\n    \n  <\/style>\n  \n  <div class=\"R1-line1\" >\n    <img src=\"https:\/\/cdn.shopify.com\/s\/files\/1\/0669\/6343\/9927\/files\/Group_970.png?v=1668752390\">\n<div class=\"R1-line2\" >\n<span >Acne Rosacea Skincare<br>\n<\/div>\n<\/a>\n<\/div>\n<\/span>\n<div style=\"font-size:16px;\">To care for your acne rosacea condition, you need to identify the triggers that cause flare-ups. For instance, cold temperatures and ultraviolet light exposure can worsen your symptoms.\n<br>\n<br>\n\nIf you're wondering how to care for your rosacea-prone skin, we'll share some recommendations scientists advise implementing in your rosacea skincare routine.\n\n<br>\n<br>\n\nFirst of all, make sure your skin barrier is in good condition. Use a gentle cleanser and avoid scrubbing or a washcloth on the affected area. Wash your face with tepid, not hot, water. Lastly, wear sunscreen daily all year round (avoid chemical sunscreen).\n<br>\n<br>\nAll this information is supported by scientific research at <p3 class=\"manage-roseacea-text3\" style=\"Font:Poppins;Weight:500;Size:24px;color:#cc4e61;\nLine height:36px;\n\">NCBI.<\/p3>\n<\/div>",
        "full_width": false,
        "show_divider": false,
        "padding_top": 36,
        "columns_mobile": "1",
        "swipe_on_mobile": true,
        "padding_bottom": 36
      }
    },
    "cca07c9f-4cdb-4793-8698-78a2c002f5bd": {
      "type": "custom-liquid",
      "settings": {
        "custom_liquid": "<style>\n   .R2-line1 {\n         \n        border-radius:10px;\n      display: flex;\n      flex-direction: row;\n      border-radius:10px;\n      justify-content: center;\n      align-items: center;\n      \n      font-size: calc(1.25em + 0.25vmin);\n    }\n@media screen and (max-width:767px){\n.R2-line1{\nwidth:100%;\n}\n.R2-line1 {\n    border-radius: 10px;\n    display: flex;\n    flex-direction: row;\n    border-radius: 10px;\n    justify-content: center;\n    align-items: center;\n    font-size: calc(2em + -3.75vmin);\n}\n}\n\n.R2-line2{\ncolor: #4a4a4a;\n    font-weight: bold;\n    margin: 20px;\n    width: 55%;\n}\n@media screen and (max-width:767px){\n.R2-line2{\nwidth:100%;\n}\n.R2-line2{\ncolor: #4a4a4a;\n    font-weight: bold;\n    margin: 4px;\n    width: 900%;\n}\n}\n    \n    .R2-line1:after {\n      background-color: #cc4e61;\n      border-radius:10px;\n      content: \"\";\n      display: inline-block;\n      height: 2px;\n      \n      \/* vertical-align: middle; *\/\n       width: 100%;\n    }\n \n    .R2-line1:after {\n      text-align: center; \nborder-radius:10px;\npadding:0 calc(0.5em + 1.25vmin);\n    }\n@media screen and (max-width:767px){\nwidth:100%;\n .R2-line1:after {\n    text-align: center;\n    border-radius: 10px;\n    padding: 0 calc(0em + 9.25vmin);\n}\n}\n\n    \n  <\/style>\n  \n  <div class=\"R2-line1\" >\n    <img src=\"https:\/\/cdn.shopify.com\/s\/files\/1\/0669\/6343\/9927\/files\/Group_970.png?v=1668752390\">\n<div class=\"R2-line2\" >\n<span >How will Red Algae help you care for Rosacea Skin?<br>\n<\/div>\n<\/a>\n<\/div>\n<\/span>\n<div style=\"font-size:16px;\">When your skin is exposed to environmental stressors such as UV rays, smoke, chemicals and extreme temperatures, it responds by producing excessive amounts of ROS. The overproduction of ROS can trigger inflammatory skin diseases like Rosacea.\n\n<br>\n<br>\n\n\nRed Algae contains carotenoids, which can fight harmful radicals, protecting you from the stress of everyday life, according to a research article published by the  <p2 class=\"manage-roseacea-text3\" style=\"Font:Poppins;Weight:500;Size:24px;color:#cc4e61;\nLine height:36px;\n\">NCBI.<\/p2> This may help you lessen your skin triggers and your Rosacea flare-ups.\n\n\n\n<br>\n<br>\nCarotenoids can potentially be used to treat chronic inflammation, according to research published by the  <p2 class=\"manage-roseacea-text3\" style=\"Font:Poppins;Weight:500;Size:24px;color:#cc4e61;\nLine height:36px;\n\">NCBI.<\/p2> They are capable of inhibiting pro-inflammatory cytokines.\nSince Red Algae contains Carotenoids and other bioactive compounds that can inhibit the production of pro-inflammatory cytokines and reduce the expression of inflammatory genes, it can be considered an effective acne rosacea natural treatment.\n<br>\n<\/div>",
        "full_width": false,
        "show_divider": false,
        "padding_top": 36,
        "columns_mobile": "1",
        "swipe_on_mobile": true,
        "padding_bottom": 36
      }
    },
    "b41e39db-190f-43b5-a68e-1fab41ff8c74": {
      "type": "custom-liquid",
      "settings": {
        "custom_liquid": "<style>\n   .line1 {\n         \n        border-radius:10px;\n      display: flex;\n      flex-direction: row;\n      border-radius:10px;\n      justify-content: center;\n      align-items: center;\n      \n      font-size: calc(1.25em + 0.25vmin);\n    }\n@media screen and (max-width:767px){\n.line1{\nwidth:100%;\n}\n.line1 {\n    border-radius: 10px;\n    display: flex;\n    flex-direction: row;\n    border-radius: 10px;\n    justify-content: center;\n    align-items: center;\n    font-size: calc(2em + -3.75vmin);\n}\n}\n\n.line2{\ncolor: #4a4a4a;\n    font-weight: bold;\n    margin: 20px;\n    width: 55%;\n}\n@media screen and (max-width:767px){\n.line2{\nwidth:100%;\n}\n.line2{\ncolor: #4a4a4a;\n    font-weight: bold;\n    margin: 4px;\n    width: 900%;\n}\n}\n    \n    .line1:after {\n      background-color: #cc4e61;\n      border-radius:10px;\n      content: \"\";\n      display: inline-block;\n      height: 2px;\n      \n      \/* vertical-align: middle; *\/\n       width: 100%;\n    }\n \n    .line1:after {\n      text-align: center; \nborder-radius:10px;\npadding:0 calc(0.5em + 1.25vmin);\n    }\n@media screen and (max-width:767px){\nwidth:100%;\n .line1:after {\n    text-align: center;\n    border-radius: 10px;\n    padding: 0 calc(0em + 9.25vmin);\n}\n}\n\n    \n  <\/style>\n  \n  <div class=\"line1\" >\n    <img src=\"https:\/\/cdn.shopify.com\/s\/files\/1\/0669\/6343\/9927\/files\/Group_970.png?v=1668752390\">\n<div class=\"line2\" >\n<span >Seacra's Red Algae Infused Gel<br>\n<\/div>\n<\/a>\n<\/div>\n<\/span>\n<div style=\"font-size:16px;\">\n\nRed algae have revolutionised the skincare industry because of their amazing qualities and potential. At Seacra, we have already proven the power of red algae by improving skin elasticity, reducing fine lines, restoring skin firmness and diminishing pores. You can check our clinical trials \n <p2 class=\"manage-roseacea-text3\" style=\"Font:Poppins;Weight:500;Size:24px;color:#cc4e61;\nLine height:36px;\n\">here.<\/p2>\n<\/div>",
        "full_width": false,
        "show_divider": false,
        "padding_top": 36,
        "columns_mobile": "1",
        "swipe_on_mobile": true,
        "padding_bottom": 36
      }
    },
    "29a56fa6-23af-4364-a00a-c368e7be209a": {
      "type": "custom-liquid",
      "settings": {
        "custom_liquid": "<style>\n   .line1 {\n         \n        border-radius:10px;\n      display: flex;\n      flex-direction: row;\n      border-radius:10px;\n      justify-content: center;\n      align-items: center;\n      \n      font-size: calc(1.25em + 0.25vmin);\n    }\n@media screen and (max-width:767px){\n.line1{\nwidth:100%;\n}\n.line1 {\n    border-radius: 10px;\n    display: flex;\n    flex-direction: row;\n    border-radius: 10px;\n    justify-content: center;\n    align-items: center;\n    font-size: calc(2em + -3.75vmin);\n}\n}\n\n.line2{\ncolor: #4a4a4a;\n    font-weight: bold;\n    margin: 20px;\n    width: 55%;\n}\n@media screen and (max-width:767px){\n.line2{\nwidth:100%;\n}\n.line2{\ncolor: #4a4a4a;\n    font-weight: bold;\n    margin: 4px;\n    width: 900%;\n}\n}\n    \n    .line1:after {\n      background-color: #cc4e61;\n      border-radius:10px;\n      content: \"\";\n      display: inline-block;\n      height: 2px;\n      \n      \/* vertical-align: middle; *\/\n       width: 100%;\n    }\n \n    .line1:after {\n      text-align: center; \nborder-radius:10px;\npadding:0 calc(0.5em + 1.25vmin);\n    }\n@media screen and (max-width:767px){\nwidth:100%;\n .line1:after {\n    text-align: center;\n    border-radius: 10px;\n    padding: 0 calc(0em + 9.25vmin);\n}\n}\n\n    \n  <\/style>\n  \n  <div class=\"line1\" >\n    <img src=\"https:\/\/cdn.shopify.com\/s\/files\/1\/0669\/6343\/9927\/files\/Group_970.png?v=1668752390\">\n<div class=\"line2\" >\n<span >Our Innovative Process<br>\n<\/div>\n<\/a>\n<\/div>\n<\/span>\n<div style=\"font-size:16px;\">\nWe've improved our red algae gel through an innovative process. We built specially designed pools within greenhouses and placed them in a nature reserve along the Mediterranean coast to grow and harvest our red algae. We then processed the algae using a cold-press method, keeping them at a safe temperature to preserve all their vitamins and bioactive compounds. Our product is clean and free from ocean contamination and delivers the highest potency available.\n<\/div>",
        "full_width": false,
        "show_divider": false,
        "padding_top": 36,
        "columns_mobile": "1",
        "swipe_on_mobile": true,
        "padding_bottom": 36
      }
    },
    "100c06a2-af8b-4fe8-af6c-2f9433123451": {
      "type": "custom-liquid",
      "settings": {
        "custom_liquid": "<style>\n   .line1 {\n         \n        border-radius:10px;\n      display: flex;\n      flex-direction: row;\n      border-radius:10px;\n      justify-content: center;\n      align-items: center;\n      \n      font-size: calc(1.25em + 0.25vmin);\n    }\n@media screen and (max-width:767px){\n.line1{\nwidth:100%;\n}\n.line1 {\n    border-radius: 10px;\n    display: flex;\n    flex-direction: row;\n    border-radius: 10px;\n    justify-content: center;\n    align-items: center;\n    font-size: calc(2em + -3.75vmin);\n}\n}\n\n.line2{\ncolor: #4a4a4a;\n    font-weight: bold;\n    margin: 20px;\n    width: 55%;\n}\n@media screen and (max-width:767px){\n.line2{\nwidth:100%;\n}\n.line2{\ncolor: #4a4a4a;\n    font-weight: bold;\n    margin: 4px;\n    width: 900%;\n}\n}\n    \n    .line1:after {\n      background-color: #cc4e61;\n      border-radius:10px;\n      content: \"\";\n      display: inline-block;\n      height: 2px;\n      \n      \/* vertical-align: middle; *\/\n       width: 100%;\n    }\n \n    .line1:after {\n      text-align: center; \nborder-radius:10px;\npadding:0 calc(0.5em + 1.25vmin);\n    }\n@media screen and (max-width:767px){\nwidth:100%;\n .line1:after {\n    text-align: center;\n    border-radius: 10px;\n    padding: 0 calc(0em + 9.25vmin);\n}\n}\n\n    \n  <\/style>\n  \n  <div class=\"line1\" >\n    <img src=\"https:\/\/cdn.shopify.com\/s\/files\/1\/0669\/6343\/9927\/files\/Group_970.png?v=1668752390\">\n<div class=\"line2\" >\n<span >Our clinical study on patients who were prone to skin diseases<br>\n<\/div>\n<\/a>\n<\/div>\n<\/span>\n<div style=\"font-size:16px;\">\nWe conducted a clinical trial on participants with various skin concerns and received wonderful feedback. 100% of volunteers with skin prone to Rosacea and redness reported a 21% reduction in redness after 28 days of using the product. This can make Red Algae gel an effective acne rosacea natural treatment.\n<\/div>",
        "full_width": false,
        "show_divider": false,
        "padding_top": 36,
        "columns_mobile": "1",
        "swipe_on_mobile": true,
        "padding_bottom": 36
      }
    },
    "9817f136-c5b2-4520-a489-0706ccd9c59b": {
      "type": "custom-liquid",
      "settings": {
        "custom_liquid": "<style>\n   .line1 {\n         \n        border-radius:10px;\n      display: flex;\n      flex-direction: row;\n      border-radius:10px;\n      justify-content: center;\n      align-items: center;\n      \n      font-size: calc(1.25em + 0.25vmin);\n    }\n@media screen and (max-width:767px){\n.line1{\nwidth:100%;\n}\n.line1 {\n    border-radius: 10px;\n    display: flex;\n    flex-direction: row;\n    border-radius: 10px;\n    justify-content: center;\n    align-items: center;\n    font-size: calc(2em + -3.75vmin);\n}\n}\n\n.line2{\ncolor: #4a4a4a;\n    font-weight: bold;\n    margin: 20px;\n    width: 55%;\n}\n@media screen and (max-width:767px){\n.line2{\nwidth:100%;\n}\n.line2{\ncolor: #4a4a4a;\n    font-weight: bold;\n    margin: 4px;\n    width: 900%;\n}\n}\n    \n    .line1:after {\n      background-color: #cc4e61;\n      border-radius:10px;\n      content: \"\";\n      display: inline-block;\n      height: 2px;\n      \n      \/* vertical-align: middle; *\/\n       width: 100%;\n    }\n \n    .line1:after {\n      text-align: center; \nborder-radius:10px;\npadding:0 calc(0.5em + 1.25vmin);\n    }\n@media screen and (max-width:767px){\nwidth:100%;\n .line1:after {\n    text-align: center;\n    border-radius: 10px;\n    padding: 0 calc(0em + 9.25vmin);\n}\n}\n\n    \n  <\/style>\n  \n  <div class=\"line1\" >\n    <img src=\"https:\/\/cdn.shopify.com\/s\/files\/1\/0669\/6343\/9927\/files\/Group_970.png?v=1668752390\">\n<div class=\"line2\" >\n<span >Seacra's Recovery & Repair Gel<br>\n<\/div>\n<\/a>\n<\/div>\n<\/span>\n<div style=\"font-size:16px;\">\nRecovery & Repair Gel contains an exclusive blend of chamomile, calendula and jojoba oil combined with the rejuvenating purity of red algae. Together, they provide the deep hydration and nourishment your skin needs to repair and recover.\n<\/div>",
        "full_width": false,
        "show_divider": false,
        "padding_top": 36,
        "columns_mobile": "1",
        "swipe_on_mobile": true,
        "padding_bottom": 36
      }
    },
    "db7ee83c-fe85-4c5c-88d8-525bd9e5a7f6": {
      "type": "custom-liquid",
      "settings": {
        "custom_liquid": "<style>\n   .line1 {\n         \n        border-radius:10px;\n      display: flex;\n      flex-direction: row;\n      border-radius:10px;\n      justify-content: center;\n      align-items: center;\n      \n      font-size: calc(1.25em + 0.25vmin);\n    }\n@media screen and (max-width:767px){\n.line1{\nwidth:100%;\n}\n.line1 {\n    border-radius: 10px;\n    display: flex;\n    flex-direction: row;\n    border-radius: 10px;\n    justify-content: center;\n    align-items: center;\n    font-size: calc(2em + -3.75vmin);\n}\n}\n\n.line2{\ncolor: #4a4a4a;\n    font-weight: bold;\n    margin: 20px;\n    width: 55%;\n}\n@media screen and (max-width:767px){\n.line2{\nwidth:100%;\n}\n.line2{\ncolor: #4a4a4a;\n    font-weight: bold;\n    margin: 4px;\n    width: 900%;\n}\n}\n    \n    .line1:after {\n      background-color: #cc4e61;\n      border-radius:10px;\n      content: \"\";\n      display: inline-block;\n      height: 2px;\n      \n      \/* vertical-align: middle; *\/\n       width: 100%;\n    }\n \n    .line1:after {\n      text-align: center; \nborder-radius:10px;\npadding:0 calc(0.5em + 1.25vmin);\n    }\n@media screen and (max-width:767px){\nwidth:100%;\n .line1:after {\n    text-align: center;\n    border-radius: 10px;\n    padding: 0 calc(0em + 9.25vmin);\n}\n}\n\n    \n  <\/style>\n  \n  <div class=\"line1\" >\n    <img src=\"https:\/\/cdn.shopify.com\/s\/files\/1\/0669\/6343\/9927\/files\/Group_970.png?v=1668752390\">\n<div class=\"line2\" >\n<span >Recover. Repair. Reuse<br>\n<\/div>\n<\/a>\n<\/div>\n<\/span>\n<div style=\"font-size:16px;\">\nRefillable and 100% recyclable packaging: Our mission is to clean up the beauty industry. We love our planet; we believe in zero waste living. After repairing your skin with our ultra-rich red algae gel, you can request to refill your bottle when it is empty.<br>\n<br>\n<p2 class=\"manage-roseacea-text3\" style=\"Font:Poppins;Weight:500;Size:24px;color:#cc4e61;\nLine height:36px;\n\">Experience Recovery & Repair Gel Today.<\/p2>\n\n<\/div>",
        "full_width": false,
        "show_divider": false,
        "padding_top": 36,
        "columns_mobile": "1",
        "swipe_on_mobile": true,
        "padding_bottom": 36
      }
    },
    "820f5893-5a1a-4ace-8519-b21e82bf0107": {
      "type": "gallery",
      "blocks": {
        "template--17262620999991__820f5893-5a1a-4ace-8519-b21e82bf0107-16710780535f0a65ac-0": {
          "type": "image",
          "settings": {
            "image": "shopify:\/\/shop_images\/Mask_group_11_335143e4-be63-4c26-a8e8-e3d7178ce657.png",
            "image_position": "center center",
            "subheading": "",
            "subheading_size": "h5",
            "heading": "",
            "heading_size": "h3",
            "link": "",
            "text_box_position": "middle-center"
          }
        }
      },
      "block_order": [
        "template--17262620999991__820f5893-5a1a-4ace-8519-b21e82bf0107-16710780535f0a65ac-0"
      ],
      "settings": {
        "per_row": 3,
        "spacing_images": 20,
        "image_height": 500,
        "apply_overlay": true,
        "full_width": false,
        "show_divider": false,
        "heading": "",
        "heading_size": "h1",
        "heading_alignment": "center",
        "heading_tag": "h2",
        "columns_mobile": "1",
        "swipe_on_mobile": true,
        "mobile_image_height": 170,
        "padding_top": 36,
        "padding_bottom": 36
      }
    },
    "a00ba81b-aad7-4cd7-a454-35e7dd74729f": {
      "type": "Blog-description-line",
      "settings": {
      }
    },
    "91844a5c-297e-4e69-95f6-791e1262901e": {
      "type": "rich-text",
      "blocks": {
        "template--17262620999991__91844a5c-297e-4e69-95f6-791e1262901e-16710783357e07698e-2": {
          "type": "button",
          "settings": {
            "button_label": "Back to Blogs",
            "button_link": "",
            "button_size": "small",
            "button_style_secondary": false
          }
        }
      },
      "block_order": [
        "template--17262620999991__91844a5c-297e-4e69-95f6-791e1262901e-16710783357e07698e-2"
      ],
      "settings": {
        "text_alignment": "center",
        "mobile_text_alignment": "center",
        "horizontal_content": false,
        "narrow": false,
        "show_divider": false,
        "use_custom_colors": false,
        "colors_text": "#212326",
        "colors_background": "#ffffff",
        "gradient_background": "",
        "padding_top": 36,
        "padding_bottom": 36
      }
    },
    "33f3a336-7b7e-488b-9a6a-f8f2f45ff9be": {
      "type": "custom-liquid",
      "settings": {
        "custom_liquid": "<hr style=\"border: 0px solid #4A4A4A;\"\/>",
        "full_width": false,
        "show_divider": false,
        "padding_top": 36,
        "columns_mobile": "1",
        "swipe_on_mobile": true,
        "padding_bottom": 36
      }
    },
    "ca712e38-8309-4f8c-9899-971cbd08b445": {
      "type": "rich-text",
      "blocks": {
        "template--17262620999991__ca712e38-8309-4f8c-9899-971cbd08b445-16710783357e07698e-2": {
          "type": "button",
          "settings": {
            "button_label": "Best Changes You Will Ever Make for Your Skin",
            "button_link": "",
            "button_size": "small",
            "button_style_secondary": false
          }
        }
      },
      "block_order": [
        "template--17262620999991__ca712e38-8309-4f8c-9899-971cbd08b445-16710783357e07698e-2"
      ],
      "settings": {
        "text_alignment": "left",
        "mobile_text_alignment": "left",
        "horizontal_content": false,
        "narrow": false,
        "show_divider": false,
        "use_custom_colors": false,
        "colors_text": "#212326",
        "colors_background": "#ffffff",
        "gradient_background": "",
        "padding_top": 36,
        "padding_bottom": 36
      }
    },
    "0f2d5989-bba1-4524-a592-2c8cb8dbaaf6": {
      "type": "custom-liquid",
      "settings": {
        "custom_liquid": "<hr style=\"border: 0px solid #4A4A4A;\"\/>",
        "full_width": false,
        "show_divider": false,
        "padding_top": 36,
        "columns_mobile": "1",
        "swipe_on_mobile": true,
        "padding_bottom": 36
      }
    },
    "3cade5f7-bde9-498f-9284-5a764db92c64": {
      "type": "rich-text",
      "blocks": {
        "template--17262620999991__3cade5f7-bde9-498f-9284-5a764db92c64-16710783357e07698e-1": {
          "type": "text",
          "settings": {
            "text": "<p>You May Also Like<\/p>",
            "text_size": "typeset3",
            "secondary_color": false
          }
        }
      },
      "block_order": [
        "template--17262620999991__3cade5f7-bde9-498f-9284-5a764db92c64-16710783357e07698e-1"
      ],
      "settings": {
        "text_alignment": "center",
        "mobile_text_alignment": "center",
        "horizontal_content": false,
        "narrow": false,
        "show_divider": false,
        "use_custom_colors": false,
        "colors_text": "#212326",
        "colors_background": "#ffffff",
        "gradient_background": "",
        "padding_top": 36,
        "padding_bottom": 36
      }
    },
    "22d2f80b-5d35-4831-aadc-a9486643b1c5": {
      "type": "multicolumn",
      "blocks": {
        "template--17262620999991__22d2f80b-5d35-4831-aadc-a9486643b1c5-1671078719c705c3a0-0": {
          "type": "column",
          "settings": {
            "image": "shopify:\/\/shop_images\/pic_1_1_3.png",
            "title": "Red Algae as an effective alternative to retinol",
            "use_custom_colors": false,
            "colors_button_label": "#ffffff",
            "colors_button_background": "#1a1b18",
            "title_size": "h4",
            "text": "<p>May 29, 2022    .    By Seacra<\/p>",
            "button_label": "",
            "button_link": "",
            "button_style_secondary": false
          }
        },
        "template--17262620999991__22d2f80b-5d35-4831-aadc-a9486643b1c5-1671078719c705c3a0-1": {
          "type": "column",
          "settings": {
            "image": "shopify:\/\/shop_images\/Blog_Thumbnail_1_2.png",
            "title": "Holiday Essentials",
            "use_custom_colors": false,
            "colors_button_label": "#ffffff",
            "colors_button_background": "#1a1b18",
            "title_size": "h4",
            "text": "<p>May 29, 2022    .    By Seacra<\/p>",
            "button_label": "",
            "button_link": "",
            "button_style_secondary": false
          }
        },
        "template--17262620999991__22d2f80b-5d35-4831-aadc-a9486643b1c5-1671078719c705c3a0-2": {
          "type": "column",
          "settings": {
            "image": "shopify:\/\/shop_images\/Mask_group_40_d89fbdb4-488c-4d87-8016-eebd712ed53e.png",
            "title": "Can we Grow old gracefully?",
            "use_custom_colors": false,
            "colors_button_label": "#ffffff",
            "colors_button_background": "#1a1b18",
            "title_size": "h4",
            "text": "<p>May 29, 2022    .    By Seacra<\/p>",
            "button_label": "",
            "button_link": "",
            "button_style_secondary": false
          }
        }
      },
      "block_order": [
        "template--17262620999991__22d2f80b-5d35-4831-aadc-a9486643b1c5-1671078719c705c3a0-0",
        "template--17262620999991__22d2f80b-5d35-4831-aadc-a9486643b1c5-1671078719c705c3a0-1",
        "template--17262620999991__22d2f80b-5d35-4831-aadc-a9486643b1c5-1671078719c705c3a0-2"
      ],
      "settings": {
        "image_ratio": "landscape",
        "image_position": "center center",
        "text_alignment": "center",
        "show_divider": false,
        "heading": "",
        "heading_size": "h1",
        "heading_alignment": "center",
        "heading_tag": "h2",
        "mobile_text_alignment": "center",
        "columns_mobile": "1",
        "swipe_on_mobile": false,
        "padding_top": 36,
        "padding_bottom": 36
      }
    },
    "3d2f4ec2-101a-4297-8c90-c7170bac4244": {
      "type": "rich-text",
      "blocks": {
        "template--17262620999991__3d2f4ec2-101a-4297-8c90-c7170bac4244-16710783357e07698e-2": {
          "type": "button",
          "settings": {
            "button_label": "View All",
            "button_link": "",
            "button_size": "small",
            "button_style_secondary": false
          }
        }
      },
      "block_order": [
        "template--17262620999991__3d2f4ec2-101a-4297-8c90-c7170bac4244-16710783357e07698e-2"
      ],
      "settings": {
        "text_alignment": "center",
        "mobile_text_alignment": "center",
        "horizontal_content": false,
        "narrow": false,
        "show_divider": false,
        "use_custom_colors": false,
        "colors_text": "#212326",
        "colors_background": "#ffffff",
        "gradient_background": "",
        "padding_top": 36,
        "padding_bottom": 36
      }
    }
  },
  "order": [
    "main",
    "a893289b-2595-43c4-bf57-ba711b1e94bc",
    "8285edb0-3d58-461d-abbe-39af17159741",
    "4fc8e1bc-a4dd-40a2-8977-fd97466699e2",
    "00b55c1f-44b3-4f89-a159-d9de3a5b4dc5",
    "018cdaa3-4f46-49ca-9691-71baf263e524",
    "cca07c9f-4cdb-4793-8698-78a2c002f5bd",
    "b41e39db-190f-43b5-a68e-1fab41ff8c74",
    "29a56fa6-23af-4364-a00a-c368e7be209a",
    "100c06a2-af8b-4fe8-af6c-2f9433123451",
    "9817f136-c5b2-4520-a489-0706ccd9c59b",
    "db7ee83c-fe85-4c5c-88d8-525bd9e5a7f6",
    "820f5893-5a1a-4ace-8519-b21e82bf0107",
    "a00ba81b-aad7-4cd7-a454-35e7dd74729f",
    "91844a5c-297e-4e69-95f6-791e1262901e",
    "33f3a336-7b7e-488b-9a6a-f8f2f45ff9be",
    "ca712e38-8309-4f8c-9899-971cbd08b445",
    "0f2d5989-bba1-4524-a592-2c8cb8dbaaf6",
    "3cade5f7-bde9-498f-9284-5a764db92c64",
    "22d2f80b-5d35-4831-aadc-a9486643b1c5",
    "3d2f4ec2-101a-4297-8c90-c7170bac4244"
  ]
}
