{
  "sections": {
    "main": {
      "type": "main-search",
      "disabled": true,
      "settings": {
        "products_per_row": 4,
        "rows_per_page": 9,
        "columns_mobile": "2",
        "pagination": "paginated",
        "enable_sticky_facet": true,
        "enable_sorting": true,
        "enable_viewing": true,
        "enable_filtering": true,
        "filter_type": "vertical",
        "enable_filtering_color_swatches": true,
        "filtering_color_swatches_add_label": false,
        "filtering_max_items": 6,
        "image_ratio": "portrait",
        "image_position": "center center",
        "enable_image_fill": true,
        "show_secondary_image": true,
        "show_vendor": true,
        "show_rating": true,
        "show_quick_buy": true,
        "enable_quick_view": true,
        "enable_color_swatches": true,
        "enable_countdown": true,
        "article_show_date": true,
        "article_show_author": false,
        "article_show_comment_count": true,
        "padding_top": 36,
        "padding_bottom": 60
      }
    },
    "88c4c3d5-c1fd-4623-944e-3480bf58bda8": {
      "type": "image-banner",
      "blocks": {
        "fc88987b-1a2a-4b34-b18b-1f8f96bdf7e8": {
          "type": "custom_liquid",
          "settings": {
            "custom_liquid": "<div style=\" position:relative;\nleft:-78px;top:-276px;\">\n<span style=\"font-size: 18px; color: #CC4E61;\"><b>Sustainable for your SKIN & OUR PLANET <\/b><\/span>\n<br>\n<span style=\"font-size: 15px;color:#4a4a4a\">In Partnership With <\/span>\n<br>\n<span style=\"font-size: 15px; color: #CC4E61;\"><b>Eden Reforestation Projects<\/b><\/span> \n<br>\n<span style=\"font-size: 25px; color: #CC4E61; position:relative; top:15px;\"><b>Our Process<\/b><\/span>\n<div style=\"width: 900px; position: relative;left: -80px\">\n\n<p style=\"font-family: 'Poppins';\nposition:relative;\nfont-style: normal;\nfont-weight: 300;\nfont-size: 17px;\nline-height: 27px;\ntext-align: left;\nleft:137px;color:#4a4a4a\">\nWe make our skincare product range in an eco-friendly & <br\/>sustainable manner by adding value to the world around us.<\/p>\n<\/div>"
          }
        }
      },
      "block_order": [
        "fc88987b-1a2a-4b34-b18b-1f8f96bdf7e8"
      ],
      "settings": {
        "image": "shopify:\/\/shop_images\/Group_1129_55-modified_1_100.png",
        "image_position": "center center",
        "text_box_position": "bottom-center",
        "text_alignment": "center",
        "image_ratio": "adapt",
        "show_text_box": false,
        "full_width": true,
        "show_divider": false,
        "mobile_text_alignment": "center",
        "mobile_image_ratio": "auto",
        "stack_images_on_mobile": true,
        "show_text_below": true,
        "colors_text": "#cc4e61",
        "colors_overlay": "#ffffff",
        "colors_overlay_opacity": 0,
        "padding_top": 0,
        "padding_bottom": 0
      }
    },
    "4c96076b-ba5d-41ab-bbde-d2690b12e2ba": {
      "type": "slideshow",
      "blocks": {
        "template--16824669929783__4c96076b-ba5d-41ab-bbde-d2690b12e2ba-1669103729fec51490-0": {
          "type": "image",
          "settings": {
            "image": "shopify:\/\/shop_images\/Group_1129_90.png",
            "image_position": "center center",
            "text_box_position": "middle-center",
            "subheading": "",
            "subheading_size": "h5",
            "heading_1": "Image slide",
            "heading_2": "Image slide",
            "heading_3": "Image slide",
            "heading_size": "h1",
            "heading_tag": "h2",
            "text": "",
            "text_size": "typeset",
            "button_label": "",
            "button_link": "",
            "button_size": "medium",
            "button_style_secondary": false
          }
        }
      },
      "block_order": [
        "template--16824669929783__4c96076b-ba5d-41ab-bbde-d2690b12e2ba-1669103729fec51490-0"
      ],
      "settings": {
        "slideshow_type": "modern",
        "text_alignment": "left",
        "image_ratio": "adapt_first",
        "autorotate": false,
        "autorotate_speed": 5,
        "full_width": true,
        "mobile_text_alignment": "left",
        "mobile_image_ratio": "300px",
        "show_text_below": false,
        "colors_text": "#1a1b18",
        "colors_background": "#ffffff",
        "colors_overlay": "#ffffff",
        "colors_overlay_opacity": 0,
        "colors_navigation_text": "#ffffff",
        "colors_navigation_background": "#1a1b18",
        "padding_top": 0,
        "padding_bottom": 36
      }
    },
    "ca03126b-a6e2-47e6-9c8c-632550e150b3": {
      "type": "custom-liquid",
      "settings": {
        "custom_liquid": "<!DOCTYPE html>\n<html>\n<head>\n<meta name=\"viewport\" content=\"width=device-width, initial-scale=1\">\n<style>\n#more {display: none;}\n<\/style>\n<\/head>\n<body>\n\n<div style=\"width: 514px;\ntext-align: center;\nleft:516px;\nposition:relative;\">\n<span \nstyle=\"font-size: 25px;\ncolor: #CC4E61;\nposition: relative;\n\"> <b>We plant a tree<\/b> <\/span><span style=\"font-size: 25px;color:#4a4a4a\"><b>with every order<\/b><\/span>\n<\/div>\n\n<p style=\"font-size: 14px; \nposition: relative;\nleft: -53px;\nwidth:111%;\nfont-family: 'Poppins';\nfont-style: normal;\nline-height: 25px;\ntext-align: center;color:#4a4a4a\">By purchasing a Seacra® product, you are helping to replenish native trees and help alleviate extreme poverty through our ‘employ to plant’ environmental partnership with Eden Reforestation Projects. Our commitment to planting a minimum of 100,000 native trees in Madagascar has already been made. This specific region has been ravaged by illegal logging and clear cutting that has destroyed the natural ecosystem.<span id=\"dots\">...<\/span><span id=\"more\">The deforestation resulting from illegal logging and clear cutting reduces the environment for animals and the reduction of rainforests has been shown to have a direct connection to global warming. In addition to the impact trees and rainforests have on the environment, they also have a direct impact on the people that rely on them.\nThe wages that are earned empower men and women who have been exposed to human trafficking, extreme poverty, or lived as refugees. They are able to support their families and work on small plot farms. Their job is very specific – reforest their nation.\nFor every Seacra® product purchased a donation is made, a donation that results in the planting of another tree.\n\n\nThe other View more button you can take it out<\/span><\/p>\n<button onclick=\"myFunction()\" id=\"myBtn\" style=\"\nbackground: #CC4E61;\nborder-radius: 63px;\npadding: 10px 28px;\ngap: 10px;\ntext-align: center;\ncolor: #FFFFFF;\nborder: none;\ncursor: pointer;\nposition: relative;\nleft:687px;font-family: 'Poppins';\nfont-style: normal;\nfont-weight: 500;\nfont-size: 24px;\nline-height: 30px;\">View more<\/button>\n\n<script>\nfunction myFunction() {\n  var dots = document.getElementById(\"dots\");\n  var moreText = document.getElementById(\"more\");\n  var btnText = document.getElementById(\"myBtn\");\n\n  if (dots.style.display === \"none\") {\n    dots.style.display = \"inline\";\n    btnText.innerHTML = \"View more\"; \n    moreText.style.display = \"none\";\n  } else {\n    dots.style.display = \"none\";\n    btnText.innerHTML = \"View less\"; \n    moreText.style.display = \"inline\";\n  }\n}\n<\/script>\n\n<\/body>\n<\/html>",
        "full_width": false,
        "show_divider": false,
        "padding_top": 100,
        "padding_bottom": 100
      }
    },
    "1ab61d16-b4ee-4ba0-9ce4-2e8efaf1b6ff": {
      "type": "video",
      "settings": {
        "cover_image": "shopify:\/\/shop_images\/Image_copy_2.jpg",
        "video_url": "",
        "description": "",
        "full_width": false,
        "show_divider": false,
        "heading": "",
        "heading_size": "h1",
        "heading_alignment": "center",
        "heading_tag": "h2",
        "padding_top": 76,
        "padding_bottom": 0
      }
    },
    "af049263-5870-4471-b2f6-6cfb923199dc": {
      "type": "image-with-text",
      "blocks": {
        "88bfe396-68c0-4152-af98-bfcb03d89441": {
          "type": "custom_liquid",
          "settings": {
            "custom_liquid": "<div style=\"position: relative; left:-50px; top:-20px;\">\n<span style=\"font-size: 24px;color: #CC4E61;\"> <b>Giving back to the <\/b><\/span><span style=\"font-size: 24px;color:#4a4a4a \"> <b>Environment<\/b><\/span>\n<\/div>\n<p style=\"font-size: 16px; font-weight:100px; line-height:27px;position:relative; left:-50px;\nwidth:800px; top:-18px;\">\nWe want Seacra to be the number one sustainable choice for your skin and for our planet.<br>\nAs we pump salt water from the sea for algae growth, it is returned to it with the same consistency.<br>\nAnd since our ‘cold press’ process does not adversely affect the residual algae, it is returned as well to the sea once the job is complete.<br>\nBy growing the red algae, we are able to lower the carbon dioxide levels in the air through photosynthesis, thereby making a positive environmental impact.<br>\nWe're committed to protecting the environment by reducing our carbon footprint and by giving back to nature. \n<\/p>\n<\/div>"
          }
        }
      },
      "block_order": [
        "88bfe396-68c0-4152-af98-bfcb03d89441"
      ],
      "settings": {
        "image": "shopify:\/\/shop_images\/Mask_group_3_89eabd71-ac5e-4a42-84aa-448ad064656f.png",
        "image_position": "center center",
        "layout": "image_first",
        "text_box_position": "middle",
        "text_alignment": "left",
        "image_ratio": "400px",
        "enlarge_content": false,
        "full_width": false,
        "show_divider": false,
        "mobile_layout": "image_first",
        "mobile_text_alignment": "left",
        "mobile_image_ratio": "auto",
        "use_custom_colors": false,
        "colors_text": "#212326",
        "colors_background": "#ffffff",
        "gradient_background": "",
        "padding_top": 80,
        "padding_bottom": 40
      }
    },
    "6b50764f-01f5-4720-bb1f-9d3dba7005dc": {
      "type": "rich-text",
      "blocks": {
        "da4a2c57-2473-4440-8e5f-60a1427957f4": {
          "type": "custom_liquid",
          "settings": {
            "custom_liquid": "<span style=\"font-size: 25px;color:#4a4a4a\"><b> Refillable <\/b><\/span><span style=\"font-size: 25px; color: #CC4E61;\"> <b>Products<\/b><\/span>"
          }
        }
      },
      "block_order": [
        "da4a2c57-2473-4440-8e5f-60a1427957f4"
      ],
      "settings": {
        "text_alignment": "center",
        "mobile_text_alignment": "center",
        "horizontal_content": false,
        "narrow": false,
        "show_divider": false,
        "use_custom_colors": false,
        "colors_text": "#212326",
        "colors_background": "#ffffff",
        "gradient_background": "",
        "padding_top": 0,
        "padding_bottom": 0
      }
    },
    "e0a99f22-7597-4053-8c20-6a7ff388f5cc": {
      "type": "image-with-text",
      "blocks": {
        "0d31dbd9-8983-4d34-814b-27314ac3c5cf": {
          "type": "custom_liquid",
          "settings": {
            "custom_liquid": "<p style=\"font-size: 16px; font-weight:100px; line-height:27px;position:relative; left:-50px;\nwidth: 686px; top:-18px;\">\nNot only is all of our packaging 100% recyclable, we’ve found a way to reduce further our carbon footprint.<br>We've created a refill range for all of our products available to purchase at a 15% discount.\n<\/p>\n<button\nstyle=\"\nbackground: #CC4E61;\nborder-radius: 63px;\npadding: 10px 28px;\ngap: 10px;\n\n    top: -13px;\n\ntext-align: center;\ncolor: #FFFFFF;\nborder: none;\ncursor: pointer;\nfont-size: 24px;\nposition: relative; left:-40px;\n\"\n> \nShop now\n<\/button>"
          }
        }
      },
      "block_order": [
        "0d31dbd9-8983-4d34-814b-27314ac3c5cf"
      ],
      "settings": {
        "image": "shopify:\/\/shop_images\/Sustainable_Final_-_1.png",
        "image_position": "center center",
        "layout": "image_first",
        "text_box_position": "middle",
        "text_alignment": "left",
        "image_ratio": "adapt",
        "enlarge_content": false,
        "full_width": false,
        "show_divider": false,
        "mobile_layout": "image_first",
        "mobile_text_alignment": "left",
        "mobile_image_ratio": "auto",
        "use_custom_colors": false,
        "colors_text": "#212326",
        "colors_background": "#ffffff",
        "gradient_background": "",
        "padding_top": 36,
        "padding_bottom": 36
      }
    },
    "481d44cb-f755-4fd4-9949-e95440d50f4c": {
      "type": "custom-liquid",
      "settings": {
        "custom_liquid": "<!DOCTYPE html>\n<html>\n<head>\n<meta name=\"viewport\" content=\"width=device-width, initial-scale=1\">\n<style>\n* {\n  box-sizing: border-box;\n}\n\n\n\n\/* Create two equal columns that floats next to each other *\/\n.column {\n  float: left;\n  width: 50%;\n  padding: 10px;\n  height: 300px; \/* Should be removed. Only for demonstration *\/\n}\n\n\n\n\/* Clear floats after the columns *\/\n.row:after {\n  content: \"\";\n  display: table;\n  clear: both;\n}\n.column h2{\n    text-align:center;\n    top:50px;\n    position:relative;\n    }\n    .column p{\n    text-align:center;\n        top:50px;\n    position:relative;\n    }\n<\/style>\n<\/head>\n<body>\n  <div class=\"row\">\n  <div class=\"column\" style=\"\">\n\n    <span style=\"font-family: 'Poppins';\n    font-style: normal;\n    font-weight: 600;\n    font-size: 24px;\n    line-height: 60px; position: relative;\n    right: -573px; top: 175px;color: #CC4E61;\"> Simply, <\/span><span style=\"font-family: 'Poppins';\n    font-style: normal;\n    font-weight: 600;\n    font-size: 24px;\n    line-height: 60px;  position: relative;\n    right: -571px; top: 175px;color:#4a4a4a\"> <b>Using less<\/b><\/span>\n    <br>\n    \n    <p style=\"position: relative; top: 160px; text-align: left; width: 941px; font-size: 16px; position: relative;\n    left: -130px;\n    text-align: right; line-height: 25px;\">By using the natural red algae extract at the core of our products, we’re able to change the way your skin<br>     behaves. We target your skin problems, efficiently, without creating side-effects.<br>\nOne product producing a myriad of benefits means fewer products are needed for healthy skin. And if fewer <br> products are needed, fewer are produced resulting in less waste and natural resources utilised.\n<\/p>\n\n  <\/div>\n\n  <div class=\"column\" style=\"\">\n    \n    <img\n          src=\"https:\/\/cdn.shopify.com\/s\/files\/1\/0669\/6343\/9927\/files\/Frame_70_4.png?v=1668173024\"\n         style=\"width: 823px; height: 538px; left: 63px; position: relative; top: -87px;\"\n          \/>\n  <\/div>\n<\/div>\n\n\n\n<\/body>\n<\/html>",
        "full_width": false,
        "show_divider": false,
        "padding_top": 36,
        "padding_bottom": 36
      }
    },
    "07955936-fb61-426a-ad01-307ee40532d4": {
      "type": "custom-liquid",
      "settings": {
        "custom_liquid": "<!DOCTYPE html>\n<html>\n  <head>\n    <title>Title of the document<\/title>\n    <style>\n      h1 {\n        font-family: sans-serif;\n        margin: 100px auto;\n        text-align: center;\n        color: black;\n        font-size: 24px;\n        max-width: 400px;\n        position: relative;\n      top: 145px;}\n           h1:before {\n        content: \"\";\n        display: block;\n        width: 800px;\n        height: 6px;\n        background: #cd5c5c;\n        top:39px;\n        left: -850px;\n        \/* top: 50%; *\/\n        position: relative;\n      }\n      h1:after {\n        content: \"\";\n        display: block;\n        width: 931px;\n        height: 6px;\n        background: #cd5c5c;\n        right: -450px;\n        \/* top: -50%; *\/\n        top:2px;\n        position: relative;\n      }\n    <\/style>\n  <\/head>\n  <body>\n    <h1>\n\n    <b style=\"position: relative;\n    top: -11px;\"> Ready to plant yours?<\/b>\n\n    <\/h1>\n  <\/body>\n<\/html>\n<button\nstyle=\"\nbackground: #CC4E61;\nborder-radius: 63px;\npadding: 10px 28px; top: 50px;\ntext-align: center;\ncolor: #FFFFFF;\nborder: none;\ncursor: pointer;\nfont-size: 20px;\nposition: relative; left:668px;\n\"\n> \nShop now\n<\/button>",
        "full_width": false,
        "show_divider": false,
        "padding_top": 36,
        "padding_bottom": 36
      }
    },
    "36e02c41-8b4c-4ab7-8c72-057c6f4ea4f9": {
      "type": "rich-text",
      "blocks": {
        "e245358d-f6a3-4cec-b74e-c13b35475a4d": {
          "type": "custom_liquid",
          "settings": {
            "custom_liquid": "<span style=\"font-size: 19px; color: #CC4E61; font-weight: bold; position:relative;top:25px;\"> Learn more about the regions where you are making a difference with<\/span>\n<div style=\"font-weight: bold; font-size: 19px;position:relative;top:23px;color:#4a4a4a\">Eden Reforestation Projects\n<\/div>"
          }
        }
      },
      "block_order": [
        "e245358d-f6a3-4cec-b74e-c13b35475a4d"
      ],
      "settings": {
        "text_alignment": "center",
        "mobile_text_alignment": "center",
        "horizontal_content": false,
        "narrow": false,
        "show_divider": false,
        "use_custom_colors": false,
        "colors_text": "#212326",
        "colors_background": "#ffffff",
        "gradient_background": "",
        "padding_top": 20,
        "padding_bottom": 0
      }
    },
    "c8c49cd7-169b-4e3b-bf6d-e153f4959cf6": {
      "type": "image-with-text",
      "blocks": {
        "62eb5af1-1a5e-4b4b-acd8-38a1082d8571": {
          "type": "custom_liquid",
          "settings": {
            "custom_liquid": "<div style=\"position: relative; left:55px; top:-20px;\">\n<span style=\"font-size: 24px;font-family:Poppins;font-style:italic;color: #CC4E61;\"> <b>Madagascar <\/b><\/span>\n<\/div>\n<p style=\"font-size: 16px; font-weight:100px; line-height:27px; position:relative; left:35px;\nwidth: 686px;font-family:Poppins;font-style:italic;color:#2f2d2d\">\nMadagascar is more than just an island from an animated movie.<br>\nIt’s a nation with over 200,000 species of plants and animals thta\ndoesn’t exist anywhere else in the world. But more than 90% of \nMadagascar’s original forests have been destroyed. displacing\nentire animal species and taking away the Malagasy’s ability\nto farm and live on the land. Entire mangrove estuaries are gone,\nleaving the bare earth to wash away into the sea. And now the\nMalagasy people have no choice but to go into debt or sell\nthemselves and their families into slavery just to survive.    \n<\/p>"
          }
        },
        "b76cc0fd-8e48-4d3c-8e9d-dc27a9c96ebf": {
          "type": "custom_liquid",
          "settings": {
            "custom_liquid": "<div style=\"position:relative;left:-50pxpx;top:400px;\nbackground-color:transparent;\n<img src=\"https:\/\/cdn.shopify.com\/s\/files\/1\/0669\/6343\/9927\/files\/Mask_group_6.png?v=1667909368\" style=\"width:457px;height:444px;\">"
          }
        }
      },
      "block_order": [
        "62eb5af1-1a5e-4b4b-acd8-38a1082d8571",
        "b76cc0fd-8e48-4d3c-8e9d-dc27a9c96ebf"
      ],
      "settings": {
        "image": "shopify:\/\/shop_images\/Mask_group_1_6b70cad9-df7a-4aed-a338-5430458c3b2c.png",
        "image_position": "80% 50%",
        "layout": "image_first",
        "text_box_position": "middle",
        "text_alignment": "left",
        "image_ratio": "adapt",
        "enlarge_content": true,
        "full_width": false,
        "show_divider": false,
        "mobile_layout": "image_first",
        "mobile_text_alignment": "left",
        "mobile_image_ratio": "auto",
        "use_custom_colors": true,
        "colors_text": "#212326",
        "colors_background": "#ffffff",
        "gradient_background": "",
        "padding_top": 48,
        "padding_bottom": 92
      }
    },
    "45941589-ffc0-4dfb-b4c2-1eaaaec5d6f1": {
      "type": "footer-above-icons",
      "blocks": {
        "template--16824669929783__45941589-ffc0-4dfb-b4c2-1eaaaec5d6f1-166876395203df80f7-0": {
          "type": "footer-above-icon",
          "settings": {
            "image": "shopify:\/\/shop_images\/Frame_34.png",
            "image_width": 44,
            "text_size": 16,
            "custom_icon": "",
            "title": "Tree Planting",
            "title_size": "h3",
            "text": "<p>We’ve planted already 25,000<br\/>trees since we start in 2021 and a<br\/>commitment to plant minimum<br\/>100,000 trees has been made. <\/p>"
          }
        },
        "template--16824669929783__45941589-ffc0-4dfb-b4c2-1eaaaec5d6f1-166876395203df80f7-1": {
          "type": "footer-above-icon",
          "settings": {
            "image": "shopify:\/\/shop_images\/Frame_35.png",
            "image_width": 32,
            "text_size": 16,
            "custom_icon": "",
            "title": "Clean Chemistry",
            "title_size": "h3",
            "text": "<p>Our ingredients are 100% natural,<br\/>organic & locally sourced with<br\/>zero harmful chemicals or<br\/>materials.<\/p>"
          }
        },
        "36226d98-cd4d-4c82-8b7a-dca45355c39d": {
          "type": "footer-above-icon",
          "settings": {
            "image": "shopify:\/\/shop_images\/Frame_36.png",
            "image_width": 36,
            "text_size": 16,
            "custom_icon": "",
            "title": "Waste Reduction",
            "title_size": "h3",
            "text": "<p>We first reduce our intake of<br\/>waste and make our packaging<br\/>options 100% recyclable with<br\/>Re\/Fill option included. <\/p>"
          }
        },
        "6372c1f9-3ae6-408c-8566-cb338e8c7354": {
          "type": "footer-above-icon",
          "settings": {
            "image": "shopify:\/\/shop_images\/Frame_37.png",
            "image_width": 25,
            "text_size": 16,
            "custom_icon": "",
            "title": "Renewable Energy",
            "title_size": "h3",
            "text": "<p>We aimed to be powered by 100%<br\/>renewable energy by the end of <br\/>2030.<\/p>"
          }
        }
      },
      "block_order": [
        "template--16824669929783__45941589-ffc0-4dfb-b4c2-1eaaaec5d6f1-166876395203df80f7-0",
        "template--16824669929783__45941589-ffc0-4dfb-b4c2-1eaaaec5d6f1-166876395203df80f7-1",
        "36226d98-cd4d-4c82-8b7a-dca45355c39d",
        "6372c1f9-3ae6-408c-8566-cb338e8c7354"
      ],
      "settings": {
        "layout": "default",
        "column_alignment": "center",
        "horizontal_content": false,
        "full_width": false,
        "show_divider": false,
        "heading": "",
        "heading_size": "h1",
        "heading_tag": "h2",
        "columns_mobile": "1",
        "swipe_on_mobile": true,
        "use_custom_colors": false,
        "colors_icon": "#ffffff",
        "colors_text": "#1a1b18",
        "colors_background": "#ffffff",
        "gradient_background": "",
        "padding_top": 36,
        "padding_bottom": 36
      }
    },
    "1153e9c0-3c13-48cf-ba95-5d6f6d61b566": {
      "type": "guarantees",
      "disabled": true,
      "blocks": {
        "template--16735531041079__1153e9c0-3c13-48cf-ba95-5d6f6d61b566-1667375837c8614a16-0": {
          "type": "guarantee",
          "settings": {
            "icon": "none",
            "icon_size": "medium",
            "custom_icon": "<img src=\"https:\/\/cdn.shopify.com\/s\/files\/1\/0669\/6343\/9927\/files\/Group_3_347b0ffb-d6d7-4747-a193-e6bed6c3ea18.png?v=1668231820\" style=\"position:relative;height:40px;\nleft:5px; width:350px;\">",
            "title": "Tree Planting",
            "title_size": "h4",
            "text": "<p>We’ve planted already 25,000<br\/>trees since we start in 2021 and a<br\/>commitment to plant minimum<br\/>100,000 trees has been made. <\/p>"
          }
        },
        "79c9ccfb-8544-4165-bc85-30f04e36ae40": {
          "type": "guarantee",
          "settings": {
            "icon": "bottle",
            "icon_size": "medium",
            "custom_icon": "<img src=\"https:\/\/cdn.shopify.com\/s\/files\/1\/0669\/6343\/9927\/files\/Group_1_37450ea6-59a5-4536-a0bf-3460e34a2030.jpg?v=1668232083\" style=\"height:50px;\nleft:5px; width:100px;\">",
            "title": "Clean Chemistry",
            "title_size": "h4",
            "text": "<p>Our ingredients are 100% natural,<br\/>organic & locally sourced with<br\/>zero harmful chemicals or<br\/>materials.<\/p>"
          }
        },
        "7331e0d6-c0d9-40c8-833d-9a0e355ce2ab": {
          "type": "guarantee",
          "settings": {
            "icon": "recycle",
            "icon_size": "medium",
            "custom_icon": "<img src=\"https:\/\/cdn.shopify.com\/s\/files\/1\/0669\/6343\/9927\/files\/Group_2_1808171c-1a21-4fed-a066-38f0e6b891ce.jpg?v=1668232138\" style=\"height:50px;\nleft:5px; width:100px;\">",
            "title": "Waste Reduction",
            "title_size": "h4",
            "text": "<p>We first reduce our intake of<br\/>waste and make our packaging<br\/>options 100% recyclable with<br\/>Re\/Fill option included. <\/p>"
          }
        },
        "template--16735531041079__1153e9c0-3c13-48cf-ba95-5d6f6d61b566-1667375837c8614a16-1": {
          "type": "guarantee",
          "settings": {
            "icon": "truck",
            "icon_size": "medium",
            "custom_icon": "<img src=\"https:\/\/cdn.shopify.com\/s\/files\/1\/0669\/6343\/9927\/files\/Frame_2_8088a1de-be08-4851-997c-731648d05f57.jpg?v=1668232253\" style=\"height:50px;\nleft:5px; width:100px;\">",
            "title": "Renewable Energy",
            "title_size": "h4",
            "text": "<p>We aimed to be powered by 100%<br\/>renewable energy by the end of <br\/>2030.<\/p>"
          }
        }
      },
      "block_order": [
        "template--16735531041079__1153e9c0-3c13-48cf-ba95-5d6f6d61b566-1667375837c8614a16-0",
        "79c9ccfb-8544-4165-bc85-30f04e36ae40",
        "7331e0d6-c0d9-40c8-833d-9a0e355ce2ab",
        "template--16735531041079__1153e9c0-3c13-48cf-ba95-5d6f6d61b566-1667375837c8614a16-1"
      ],
      "settings": {
        "layout": "default",
        "column_alignment": "center",
        "horizontal_content": false,
        "full_width": false,
        "show_divider": false,
        "heading": "",
        "heading_size": "h1",
        "heading_tag": "h2",
        "columns_mobile": "1",
        "swipe_on_mobile": true,
        "use_custom_colors": false,
        "colors_icon": "#ffffff",
        "colors_text": "#1a1b18",
        "colors_background": "#ffffff",
        "gradient_background": "",
        "padding_top": 36,
        "padding_bottom": 36
      }
    },
    "b4478a2f-7761-40bc-9989-eadbd256957b": {
      "type": "rich-text",
      "blocks": {
        "20453b41-e04b-4e06-95c1-dd0c7522faaa": {
          "type": "custom_liquid",
          "settings": {
            "custom_liquid": ""
          }
        }
      },
      "block_order": [
        "20453b41-e04b-4e06-95c1-dd0c7522faaa"
      ],
      "settings": {
        "text_alignment": "center",
        "mobile_text_alignment": "left",
        "horizontal_content": false,
        "narrow": false,
        "show_divider": false,
        "use_custom_colors": false,
        "colors_text": "#212326",
        "colors_background": "#ffffff",
        "gradient_background": "",
        "padding_top": 0,
        "padding_bottom": 0
      }
    },
    "779d42f2-355e-4c59-9411-fc2f29847133": {
      "type": "rich-text",
      "settings": {
        "text_alignment": "center",
        "mobile_text_alignment": "center",
        "horizontal_content": false,
        "narrow": false,
        "show_divider": false,
        "use_custom_colors": false,
        "colors_text": "#212326",
        "colors_background": "#ffffff",
        "gradient_background": "",
        "padding_top": 0,
        "padding_bottom": 0
      }
    },
    "540551ba-cacc-4dab-9c0c-4f93ddae501d": {
      "type": "custom-liquid",
      "settings": {
        "custom_liquid": "<center>\n<div style=\"position:relative;top:120px;line-height:155%\n\">\n<span style=\"font-size: 25px;color:#CC4E61;\"><b> Get 10% off for your <\/b><\/span><span style=\"font-size: 25px; color: #4A4A4A;\"><b>first order<\/b><\/span>\n\n<div style=\"width: 900px; position: relative;left: 14px\";>\n<center>\n<p style=\"font-size: 22px;line-height:30px;color:#4a4a4a\">\nJoin us for exclusive offers, product launches, skincare tips & tricks and more.\n(Plus a few surprises along the way)\n<\/p>\n<\/div>",
        "full_width": false,
        "show_divider": false,
        "padding_top": 36,
        "padding_bottom": 36
      }
    },
    "a83514c9-4ef3-4b6d-a76b-6379fcc639a6": {
      "type": "newsletter",
      "blocks": {
        "template--16735531041079__a83514c9-4ef3-4b6d-a76b-6379fcc639a6-166737583621c20883-2": {
          "type": "email_form",
          "settings": {
          }
        }
      },
      "block_order": [
        "template--16735531041079__a83514c9-4ef3-4b6d-a76b-6379fcc639a6-166737583621c20883-2"
      ],
      "settings": {
        "text_alignment": "center",
        "mobile_text_alignment": "center",
        "full_width": false,
        "show_divider": false,
        "colors_text": "#1a1b18",
        "colors_border": "{{ shop.brand.colors.secondary[1].background }}",
        "colors_background": "{{ shop.brand.colors.secondary[1].background }}",
        "gradient_background": "",
        "padding_top": 0,
        "padding_bottom": 0
      }
    },
    "6287463e-daee-497c-80f7-7657bd9f79e4": {
      "type": "custom-liquid",
      "settings": {
        "custom_liquid": "<center>\n<button\nstyle=\"\nbackground: #CC4E61;\nborder-radius: 63px;\npadding: 10px 28px;\ngap: 10px;\ntext-align: center;\ncolor: #FFFFFF;\nborder: none;\ncursor: pointer;\nposition: relative;\ntop:-53px;\nwidth:154px;\nfont-size:24px;\n\"\n> \nSubscribe\n<\/button>",
        "full_width": false,
        "show_divider": false,
        "padding_top": 0,
        "padding_bottom": 0
      }
    },
    "8be4a607-b9d8-4de1-9e95-3692ab8c516c": {
      "type": "custom-liquid",
      "disabled": true,
      "settings": {
        "custom_liquid": "<!DOCTYPE html>\n<html>\n    <head>\n<style>\nbody {\n  font-family: \"Poppins\";\n  background: 00ee0e;\n  box-sizing: border-box;\n}\n\n\n\n#grid {\n  display: flex;\n   flex-wrap: wrap;\n  position: relative;\n  margin: 10px -111px;\n}\n#grid .f1{\n    width:400px;\n    position:relative;\n    margin-left:67px;\n}\n#grid .f2{\n    width:402px;\n    position:relative;\n    margin-left:25px;\n}\n#grid .f3{\n    width:403px;\n    position:relative;\n    margin-left:20px;\n}\n#grid .f4{\n    width:365px;\n    position:relative;\n    margin-left:-45px;\n}\nimg {\n  align-items: center;\n  left: 47px;\n  position: relative;\n}\n#grid p {\n  font-family: \"Poppins\";\n  font-style: normal;\n  font-weight: 500;\n  font-size: 16px;\n  line-height: 24px;\n  text-align: center;\n  color: #cc4e61;\n  top:10px;\n}\n#grid span {\n  font-family: \"Poppins\";\n  font-style: normal;\n  font-weight: 400;\n  font-size: 16px;\n  line-height: 24px;\n  text-align: center;\n  color: #4a4a4a;\n  top:-10px;\n  position:relative;\n}\n\n\n\n<\/style>\n  <\/head>\n    <body>\n     <div classname=\"container\">\n    <div id=\"grid\">\n\n\n\n     <div class=\"f1\" style=\"padding: 10px 103px\">\n    <img src=\"https:\/\/cdn.shopify.com\/s\/files\/1\/0669\/6343\/9927\/files\/Vector-1_d798b41b-59e5-4393-bcd4-a0b9bc903d32.png?v=1667908104\"\/>\n    <p>Free & Fast<\/p>\n    <span>Delivery Across the UK<\/span>\n   <\/div>\n\n\n\n  <div class=\"f2\" style=\"padding: 10px 137px\" >\n    <img src=\"https:\/\/cdn.shopify.com\/s\/files\/1\/0669\/6343\/9927\/files\/Group-2_272ae77b-63bc-4c7d-8810-e2a36238f437.png?v=1667908104\" style=\"left:20px\"\/>\n    <p>Free Returns<\/p>\n    <span >Within 30 days<\/span>\n   <\/div>\n\n\n\n  <div class=\"f3\" style=\"padding: 10px 72px\">\n    <img src=\"https:\/\/cdn.shopify.com\/s\/files\/1\/0669\/6343\/9927\/files\/Group-4_45baf7e6-5cc8-4ea2-b88d-e2c3cc114349.png?v=1667908104\"\/>\n    <p style=\" position:relative;left:-40px\">97% Success<\/p>\n    <span  style=\"top:-4px; position:relative;\">Rate in clinical trials<\/span>\n   <\/div>\n\n\n\n  <div class=\"f4\" style=\"padding: 10px 48px\">\n    <img src=\"https:\/\/cdn.shopify.com\/s\/files\/1\/0669\/6343\/9927\/files\/Group-3_5b2efb9c-d1b8-41c9-b5a6-3469dcabeffc.png?v=1667908104\"  style=\"left:106px\"\/>\n    <p>Partenered<\/p>\n    <span>With Eden Reforestation Project<\/span>\n   <\/div>\n<\/div>\n<\/div>\n    <\/body>\n<\/html>",
        "full_width": false,
        "show_divider": false,
        "padding_top": 36,
        "padding_bottom": 36
      }
    },
    "eb6c3730-3df5-48bb-9274-b263a59a9310": {
      "type": "footer-above-icons",
      "blocks": {
        "template--16824669929783__eb6c3730-3df5-48bb-9274-b263a59a9310-166876395203df80f7-0": {
          "type": "footer-above-icon",
          "settings": {
            "image": "shopify:\/\/shop_images\/Frame_33.png",
            "image_width": 80,
            "text_size": 16,
            "custom_icon": "",
            "title": "Free & Fast",
            "title_size": "h3",
            "text": "<p>Delivery Across the UK<\/p>"
          }
        },
        "template--16824669929783__eb6c3730-3df5-48bb-9274-b263a59a9310-166876395203df80f7-1": {
          "type": "footer-above-icon",
          "settings": {
            "image": "shopify:\/\/shop_images\/Group_4_26323ead-cc44-48bc-8adf-b062c52c3e37.png",
            "image_width": 72,
            "text_size": 16,
            "custom_icon": "",
            "title": "Free Returns",
            "title_size": "h3",
            "text": "<p>Within 30 days<\/p>"
          }
        },
        "24b585ce-b54c-4f89-aa6a-37847e5ba933": {
          "type": "footer-above-icon",
          "settings": {
            "image": "shopify:\/\/shop_images\/Group_5_69a4ae63-f403-4620-a5b4-43a0fab7657f.png",
            "image_width": 60,
            "text_size": 16,
            "custom_icon": "",
            "title": "97% Success",
            "title_size": "h3",
            "text": "<p>Rate in clinical trials<\/p>"
          }
        },
        "a0054009-cd0f-40b5-9951-7039a999e769": {
          "type": "footer-above-icon",
          "settings": {
            "image": "shopify:\/\/shop_images\/Group_6_49aac806-5ea7-4439-b976-169c71166201.png",
            "image_width": 60,
            "text_size": 16,
            "custom_icon": "",
            "title": "Partenered",
            "title_size": "h3",
            "text": "<p>With Eden Reforestation Project<\/p>"
          }
        }
      },
      "block_order": [
        "template--16824669929783__eb6c3730-3df5-48bb-9274-b263a59a9310-166876395203df80f7-0",
        "template--16824669929783__eb6c3730-3df5-48bb-9274-b263a59a9310-166876395203df80f7-1",
        "24b585ce-b54c-4f89-aa6a-37847e5ba933",
        "a0054009-cd0f-40b5-9951-7039a999e769"
      ],
      "settings": {
        "layout": "default",
        "column_alignment": "center",
        "horizontal_content": false,
        "full_width": false,
        "show_divider": false,
        "heading": "",
        "heading_size": "h1",
        "heading_tag": "h2",
        "columns_mobile": "1",
        "swipe_on_mobile": true,
        "use_custom_colors": false,
        "colors_icon": "#ffffff",
        "colors_text": "#1a1b18",
        "colors_background": "#ffffff",
        "gradient_background": "",
        "padding_top": 36,
        "padding_bottom": 36
      }
    }
  },
  "order": [
    "main",
    "88c4c3d5-c1fd-4623-944e-3480bf58bda8",
    "4c96076b-ba5d-41ab-bbde-d2690b12e2ba",
    "ca03126b-a6e2-47e6-9c8c-632550e150b3",
    "1ab61d16-b4ee-4ba0-9ce4-2e8efaf1b6ff",
    "af049263-5870-4471-b2f6-6cfb923199dc",
    "6b50764f-01f5-4720-bb1f-9d3dba7005dc",
    "e0a99f22-7597-4053-8c20-6a7ff388f5cc",
    "481d44cb-f755-4fd4-9949-e95440d50f4c",
    "07955936-fb61-426a-ad01-307ee40532d4",
    "36e02c41-8b4c-4ab7-8c72-057c6f4ea4f9",
    "c8c49cd7-169b-4e3b-bf6d-e153f4959cf6",
    "45941589-ffc0-4dfb-b4c2-1eaaaec5d6f1",
    "1153e9c0-3c13-48cf-ba95-5d6f6d61b566",
    "b4478a2f-7761-40bc-9989-eadbd256957b",
    "779d42f2-355e-4c59-9411-fc2f29847133",
    "540551ba-cacc-4dab-9c0c-4f93ddae501d",
    "a83514c9-4ef3-4b6d-a76b-6379fcc639a6",
    "6287463e-daee-497c-80f7-7657bd9f79e4",
    "8be4a607-b9d8-4de1-9e95-3692ab8c516c",
    "eb6c3730-3df5-48bb-9274-b263a59a9310"
  ]
}
