{
  "sections": {
    "main": {
      "type": "main-page",
      "settings": {
        "narrow": false,
        "padding_top": 60,
        "padding_bottom": 60
      }
    },
    "a8fbaa91-15a7-4e23-a918-7e40b19d4747": {
      "type": "custom-liquid",
      "settings": {
        "custom_liquid": "<!DOCTYPE html>\n<html lang=\"en\">\n  <head>\n    <meta charset=\"UTF-8\" \/>\n    <title>collagen drink slider<\/title>\n    <link rel=\"stylesheet\" href=\".\/style.css\" \/>\n    <style>\n        \/*Обнуление*\/\n*,\n*:before,\n*:after {\n  padding: 0;\n  margin: 0;\n  border: 0;\n  box-sizing: border-box;\n}\n.row{\n  display:flex;\n  width: 100%;\n}\n.column{\n  width:40%;\n\n}\n.column2{\n  width:70%;\n\n}\n.wrapper {\n  height: 100%;\n  padding: 50px;\n  display: flex;\n  justify-content: center;\n  align-items: center;\n}\n\n@media (max-width: 767px) {\n  .wrapper {\n    padding: 50px 10px;\n  }\n}\n\n.slick-slider {\n  min-width: 0;\n}\n\n.slick-list {\n  overflow: hidden;\n}\n\n.slick-track {\n  display: flex;\n  align-items: flex-start;\n}\n\n.slider {\n  position: relative;\n  padding: 0px 60px;\n}\n\n@media (max-width: 767px) {\n  .slider {\n    padding: 0px 40px;\n  }\n  .row{\n    flex-direction:column;\n  }\n}\n\n.slider .slick-arrow {\n  position: absolute;\n  top: 50%;\n  margin: -20px 0px 0px 0px;\n  z-index: 10;\n  font-size: 0;\n  width: 30px;\n  height: 30px;\n}\n.slider .slick-arrow.slick-prev {\n  left: 0;\n  background: url(\"https:\/\/cdn.shopify.com\/s\/files\/1\/0669\/6343\/9927\/files\/Vector_37.png?v=1673432224\") 0\n    0 \/ 100% no-repeat;\n}\n.slider .slick-arrow.slick-next {\n  right: 0;\n  background: url(\"https:\/\/cdn.shopify.com\/s\/files\/1\/0669\/6343\/9927\/files\/Vector_36.png?v=1673432224\") 0 0 \/ 100% no-repeat;\n}\n.slider .slick-arrow.slick-disabled {\n  opacity: 0.2;\n}\n\n.slider__item {\n  padding: 0px 15px;\n}\n.slider__item img {\n  max-width: 100%;\n}\n\/* @media (max-width:768px){\n  .row{\n    flex-direction:column;\n  }\n} *\/\n    <\/style>\n  <\/head>\n  <body>\n    <!-- partial:index.partial.html -->\n    <section class=\"row\">\n      <div class=\"column\">\n        <img\n          src=\"https:\/\/cdn.shopify.com\/s\/files\/1\/0669\/6343\/9927\/files\/Group_1670_1.png?v=1673429319\"\n        \/>\n      <\/div>\n      <div class=\"column2\">\n        <div class=\"wrapper\">\n          <!-- Контент -->\n\n          <div class=\"slider\">\n            <div class=\"slider__item\">\n              <!-- <div style=\"background: #cc4e61; margin: 10px; color:fff;\">\n                <h1>Antioxidant Activity<\/h1>\n                <p>\n                  We don’t want anyone to lose their glow. Collagen makes up\n                  over 70% of our skin which keeps our complexions plump, fresh\n                  and hydrated. But as we age, our natural collagen depletes.\n                  Formulated with peptan, ceramosidesand Seacrared algae, Glow\n                  Shot, is your ultimate daily collagen dose. Oh, and did we\n                  mention it also comes in three tantalising flavours?\n                <\/p>\n              <\/div> -->\n              <img src=\"https:\/\/cdn.shopify.com\/s\/files\/1\/0669\/6343\/9927\/files\/Group_1677_2.png?v=1673431495\"\n\t\t        alt=\"\">\n            <\/div>\n            <div class=\"slider__item\">\n              <img\n                src=\"https:\/\/cdn.shopify.com\/s\/files\/1\/0669\/6343\/9927\/files\/Group_1678.png?v=1673431582\"\n                alt=\"\"\n              \/>\n            <\/div>\n            <div class=\"slider__item\">\n              <img\n                src=\"https:\/\/cdn.shopify.com\/s\/files\/1\/0669\/6343\/9927\/files\/Group_1671_1.png?v=1673431824\"\n                alt=\"\"\n              \/>\n            <\/div>\n            <div class=\"slider__item\">\n              <img\n                src=\"https:\/\/cdn.shopify.com\/s\/files\/1\/0669\/6343\/9927\/files\/Group_1672_1.png?v=1673431865\"\n                alt=\"\"\n              \/>\n            <\/div>\n            <div class=\"slider__item\">\n              <img\n                src=\"https:\/\/cdn.shopify.com\/s\/files\/1\/0669\/6343\/9927\/files\/Group_1673.png?v=1673431916\"\n                alt=\"\"\n              \/>\n            <\/div>\n            <div class=\"slider__item\">\n              <img\n                src=\"https:\/\/cdn.shopify.com\/s\/files\/1\/0669\/6343\/9927\/files\/Group_1674.png?v=1673431940\"\n                alt=\"\"\n              \/>\n            <\/div>\n\t\t\t<div class=\"slider__item\">\n\t\t\t\t<img\n\t\t\t\t  src=\"https:\/\/cdn.shopify.com\/s\/files\/1\/0669\/6343\/9927\/files\/Group_1675.png?v=1673432031\"\n\t\t\t\t  alt=\"\"\n\t\t\t\t\/>\n\t\t\t  <\/div>\n\t\t\t  <div class=\"slider__item\">\n\t\t\t\t<img\n\t\t\t\t  src=\"https:\/\/cdn.shopify.com\/s\/files\/1\/0669\/6343\/9927\/files\/Group_1676_1.png?v=1673432031\"\n\t\t\t\t  alt=\"\"\n\t\t\t\t\/>\n\t\t\t  <\/div>\n          <\/div>\n        <\/div>\n      <\/div>\n    <\/section>\n    <!-- partial -->\n    <script src=\"https:\/\/cdnjs.cloudflare.com\/ajax\/libs\/jquery\/3.4.1\/jquery.min.js\"><\/script>\n    <script src=\"https:\/\/cdnjs.cloudflare.com\/ajax\/libs\/slick-carousel\/1.9.0\/slick.min.js\"><\/script>\n    <script >\n$(document).ready(function() {\n  $(\".slider\").slick({\n    arrows: true,\n    dots: false,\n    slidesToShow: 2,\n    autoplay: true,\n    speed: 900,\n    autoplaySpeed: 700,\n    responsive: [\n      {\n        breakpoint: 768,\n        settings: {\n          slidesToShow: 1\n        }\n      },\n      {\n        breakpoint: 550,\n        settings: {\n          slidesToShow: 1\n        }\n      }\n    ]\n  });\n});\n    <\/script>\n  <\/body>\n<\/html>",
        "full_width": false,
        "show_divider": false,
        "padding_top": 36,
        "columns_mobile": "1",
        "swipe_on_mobile": true,
        "padding_bottom": 36
      }
    }
  },
  "order": [
    "main",
    "a8fbaa91-15a7-4e23-a918-7e40b19d4747"
  ]
}
