{
  "sections": {
    "main": {
      "type": "main-product",
      "disabled": true,
      "settings": {
        "enable_sticky_info": true,
        "media_position": "left",
        "media_size": "medium",
        "gallery_layout": "thumbnail_slider",
        "image_ratio": "adapt_first",
        "show_thumbnails": true,
        "hide_variants": true,
        "enable_image_zoom": true,
        "enable_video_looping": false,
        "mobile_image_ratio": "adapt",
        "show_mobile_thumbnails": true,
        "padding_top": 36,
        "padding_bottom": 92
      }
    },
    "af4367ad-9bd8-42c9-a8ad-cd47dda43fe9": {
      "type": "image-banner",
      "blocks": {
        "63faa7ad-742c-4ad7-9bcf-457c6376b284": {
          "type": "custom_liquid",
          "settings": {
            "custom_liquid": "<style>\n  .banner-blur {\n    width: 80%;\n    line-height: 1.5;\n    margin: -6% 0;\n    margin-left: 15%;\n    padding: 1.5rem 2rem 3rem 2rem;\n    text-align: center;\n    overflow: hidden;\n    color: #ffffff;\n    -webkit-backdrop-filter: blur(37.6667px);\n    -moz-backdrop-filter: blur(37.6667px);\n    -o-backdrop-filter: blur(37.6667px);\n    -ms--backdrop-filter: blur(37.6667px);\n    background: rgba(217, 217, 217, 0.1);\n    box-shadow: inset 37.6667px -37.6667px 37.6667px rgb(165 165 165 \/ 10%), inset -37.6667px 37.6667px 37.6667px rgb(255 255 255 \/ 10%);\n    backdrop-filter: blur(37.6667px);\n    border-radius: 30px 0px 29px;\n  }\n\n  .small {\n    font-size: 14px;\n  }\n  .regular-size {\n    font-size: 18px; ;\n  }\n  .large-text {\n    font-size: 23px; font-weight:bold;\n  }\n  @media screen and (max-width: 767px) {\n    .banner-blur {\n      width: 100%;\n      margin-left: 0%;\n      margin-top: -15%;\n      color: #4a4a4a;\n    }\n    .large-text {\n      font-size: 15px;\n    }\n    .small {\n      font-size: 11px;\n    }\n    .regular-size {\n      font-size: 12px;\n    }\n  }\n<\/style>\n<div class=\"banner-blur\">\n  <span class=\"large-text\">Clinically proven confidence<\/span><br>\n  <span class=\"regular-size\"> Our products are clinically tested and approved by you.<\/span><br>\n  <span class=\"small\">We tested our products accross multiple complexions and skin<br>complaints, with a success rate of over <b style=\"font-size:30px;\">97% <\/b>within 28 days.<\/span>\n<\/div>"
          }
        }
      },
      "block_order": [
        "63faa7ad-742c-4ad7-9bcf-457c6376b284"
      ],
      "settings": {
        "image": "shopify:\/\/shop_images\/Group_498_10_acd4fd56-1ace-4dad-99d8-5b74fd9904d7.jpg",
        "image_position": "center center",
        "text_box_position": "bottom-center",
        "text_alignment": "center",
        "image_ratio": "adapt",
        "show_text_box": false,
        "full_width": true,
        "show_divider": false,
        "mobile_text_alignment": "center",
        "mobile_image_ratio": "auto",
        "stack_images_on_mobile": true,
        "show_text_below": true,
        "colors_text": "#ffffff",
        "colors_overlay": "#000000",
        "colors_overlay_opacity": 0,
        "padding_top": 0,
        "padding_bottom": 0
      }
    },
    "28c9af45-1fbe-4584-a182-ef4944b481ab": {
      "type": "rich-text",
      "blocks": {
        "890b1196-de78-4a03-bc78-204330d92bbb": {
          "type": "custom_liquid",
          "settings": {
            "custom_liquid": "<span style=\"font-family: 'Poppins';\nfont-style: normal;\nfont-weight: 500;\nfont-size: 32px;\nline-height: 48px;\n\/* identical to box height *\/\n\ntext-align: center;\n\ncolor: #4A4A4A;\">See the difference<\/span><div><span style=\"font-family: 'Poppins';\nfont-style: normal;\nfont-weight: 400;\nfont-size: 32px;\nline-height: 48px;\n\/* identical to box height *\/\n\ntext-align: center;\n\ncolor: #CC4E61;\">Real Skin is Beautiful\n<\/span>\n<br>\n<span style=\"font-family: 'Poppins';\nfont-style: normal;\nfont-weight: 400;\nfont-size: 20px;\nline-height: 30px;\n\/* identical to box height *\/\n\ntext-align: center;\n\ncolor: #4A4A4A;\">See for yourself by sliding the bar<\/span><div>\n<\/span>\n<br>\n<br>"
          }
        }
      },
      "block_order": [
        "890b1196-de78-4a03-bc78-204330d92bbb"
      ],
      "settings": {
        "text_alignment": "center",
        "mobile_text_alignment": "center",
        "horizontal_content": false,
        "narrow": false,
        "show_divider": false,
        "use_custom_colors": false,
        "colors_text": "#212326",
        "colors_background": "#ffffff",
        "gradient_background": "",
        "padding_top": 36,
        "padding_bottom": 36
      }
    },
    "fbe431ed-5c35-4869-a2cb-c4c3d87dbe3e": {
      "type": "custom-liquid",
      "settings": {
        "custom_liquid": "<br>\n<head>\n<meta name=\"viewport\" content=\"width=device-width, initial-scale=1\">\n<style>\n* {\n  box-sizing: border-box;\n}\n\n\n.sec {\n  float: left;\n  width: 50%;\n  padding: 10px;\n  height: 300px; \n  position:relative;\n  top:10px;\nleft:-90px;\n}\n\n.carbon_main:after {\n  content: \"\";\n  display: table;\n  clear: both;\n\n}\n\n.alisha-customer-acne_slider {\n        margin: 60px auto;\n        max-width: 1200px;\n      }\n      .alisha-customer-acne_slider {\n        flex: 1 1 0;\n      }\n\n      .inner {\n        padding: 6px;\n      }\n\n      img {\n        width: 100%;\n        height: auto;\n      }\n      \/* img:hover {\n        opacity: 0.9;\n      } *\/\n\n      .ba-slider {\n    position: relative;\n    overflow: hidden;\n  \n  }\n  \n  .ba-slider img {\n    width: 100%;\n    height: 100%;\n    display:block;\n  }\n  \n  .ba-slider .resize {\n    position: absolute;\n    top:0;\n    left: 0;\n    height: 100%;\n    width: 50%;\n    overflow: hidden;\n  }\n  \n  .handle {\n    position:absolute; \n    left:50%;\n    top:0;\n    bottom:0;\n    width:4px;\n    margin-left:-2px;\n  \n    background: #FFFFFF;\n    cursor: ew-resize;\n  }\n  \n  .handle:after {\n      position: absolute;\n      top: 50%;\n      width: 68px;\n      height: 67px;\n      margin: -32px 0 0 -32px;\n  \n      \/* content:'\\21d4'; *\/\n      content:url('https:\/\/cdn.shopify.com\/s\/files\/1\/0669\/6343\/9927\/files\/Vector_15.png?v=1669018900');\n      color:#CC4E61;\n      font-weight:bold;\n      font-size:36px;\n      text-align:center;\n      line-height:64px;\n    \/* background-image:url(.\/Group\\ 928.png); *\/\n      background: #FFFFFF; \n      border:3px solid #FFFFFF; \/* darken(@orange, 5%) *\/\n      border-radius: 50%;\n      transition:all 0.3s ease;\n      box-shadow:\n        0 2px 6px rgba(0,0,0,.3), \n        inset 0 2px 0 rgba(255,255,255,.5),\n        inset 0 60px 50px -30px #FFFFFF; \/* lighten(@orange, 20%)*\/ \n  }\n  \n  .handle.draggable:after {\n      width: 68px;\n      height: 67px;\n      margin: -32px 0 0 -32px;\n      line-height:50px;\n      font-size:30px;\n  }\n  .dev .slick-list\n{\n    position: absolute;\n\n    display: block;\n    overflow: hidden;\n\n    margin: 0;\n    padding: 0;\n}\n.one-slider{\n    \/* display:flex; *\/\n    flex-direction: column;\n}\n\n.img_content{\n    flex-direction: column;\n}\n.title {\n        text-align: center;\n        margin-top: 60px;\n        font-family: 'Poppins';\n        font-style: normal;\n        font-weight: 600;\n        font-size: 40px;\n        line-height: 60px;\n        text-align: center;\n        color: #CC4E61;\n      }\n\n@media screen and (max-width: 600px) {\n  .sec {\n    width: 100%;\n    height: 100%;\n  }\n}\n<\/style>\n<\/head>\n<body>\n\n\n<div class=\"carbon_main\">\n   <div class=\"sec\" >\n    <div class=\"one-slider\">\n        <div class=\"ba-slider\" style=\"position: absolute;left: 500px;width: 463px;top:-118px;\">\n\n            <img src=\"https:\/\/cdn.shopify.com\/s\/files\/1\/0669\/6343\/9927\/files\/MicrosoftTeams-image7dfb42950efb84556e517c8ba692901dec171e12f472534be966fc20efa9636e_1_2.jpg?v=1669781939\">\n            <div class=\"resize\">\n                <img src=\"https:\/\/cdn.shopify.com\/s\/files\/1\/0669\/6343\/9927\/files\/MicrosoftTeams-image623588dac018a0fe847b2e0a282fe12009d6fd938b9982860dd37da31ce54811_1_2.jpg?v=1669781935\">\n            <\/div>\n            <span class=\"handle\"><\/span>\n         <\/div>\n         <br\/>\n         <br\/>\n                  <div style=\"position:absolute;right: -342px; top:250px;width: 467px;\"> \n                   <img src=\"https:\/\/cdn.shopify.com\/s\/files\/1\/0669\/6343\/9927\/files\/Group_1035.jpg?v=1669357137\"\/>\n                  <\/div>\n    <\/div>\n  <\/div>\n\n <\/div>\n\n<\/div>\n\n<\/body>\n\n<script src=\"https:\/\/cdnjs.cloudflare.com\/ajax\/libs\/jquery\/2.1.3\/jquery.min.js\"><\/script>\n<script>\n\n\n\n\n    \/\/   comparision slider\n\n    \/\/ Call & init\n      $(document).ready(function(){\n          $('.ba-slider').each(function(){\n            var cur = $(this);\n            \/\/ Adjust the slider\n            var width = cur.width()+'px';\n            cur.find('.resize img').css('width', width);\n            \/\/ Bind dragging events\n            drags(cur.find('.handle'), cur.find('.resize'), cur);\n          });\n        });\n        \n        \/\/ Update sliders on resize.\n        \/\/ We all do it: i.imgur.com\/YkbaV.gif\n        $(window).resize(function(){\n          $('.ba-slider').each(function(){\n            var cur = $(this);\n            var width = cur.width()+'px';\n            cur.find('.resize img').css('width', width);\n          });\n        });\n\n        function drags(dragElement, resizeElement, container) {\n        \n          \/\/ Initialize the dragging event on mousedown.\n          dragElement.on('mousedown touchstart', function(e) {\n            \n            dragElement.addClass('draggable');\n            resizeElement.addClass('resizable');\n\n            \/\/ Check if it's a mouse or touch event and pass along the correct value\n            var startX = (e.pageX) ? e.pageX : e.originalEvent.touches[0].pageX;\n            \n            \/\/ Get the initial position\n            var dragWidth = dragElement.outerWidth(),\n            posX = dragElement.offset().left + dragWidth - startX,\n            containerOffset = container.offset().left,\n            containerWidth = container.outerWidth();\n            \n            \/\/ Set limits\n            minLeft = containerOffset + 10;\n            maxLeft = containerOffset + containerWidth - dragWidth - 10;\n            \n            \/\/ Calculate the dragging distance on mousemove.\n            dragElement.parents().on(\"mousemove touchmove\", function(e) {\n              \n              \/\/ Check if it's a mouse or touch event and pass along the correct value\n              var moveX = (e.pageX) ? e.pageX : e.originalEvent.touches[0].pageX;\n              console.log(startX, e.pageX);\n              leftValue = moveX + posX - dragWidth;\n              \n              \/\/ Prevent going off limits\n              if ( leftValue < minLeft) {\n                leftValue = minLeft;\n              } else if (leftValue > maxLeft) {\n                leftValue = maxLeft;\n              }\n              \n              \/\/ Translate the handle's left value to masked divs width.\n              widthValue = (leftValue + dragWidth\/2 - containerOffset)*100\/containerWidth+'%';\n                    \n              \/\/ Set the new values for the slider and the handle. \n              \/\/ Bind mouseup events to stop dragging.\n              $('.draggable').css('left', widthValue).on('mouseup touchend touchcancel', function () {\n                $(this).removeClass('draggable');\n                resizeElement.removeClass('resizable');\n              });\n              $('.resizable').css('width', widthValue);\n            }).on('mouseup touchend touchcancel', function(){\n              dragElement.removeClass('draggable');\n              resizeElement.removeClass('resizable');\n            });\n            e.preventDefault();\n          }).on('mouseup touchend touchcancel', function(e){\n            dragElement.removeClass('draggable');\n            resizeElement.removeClass('resizable');\n          });\n        }\n    <\/script>",
        "full_width": false,
        "show_divider": false,
        "padding_top": 36,
        "columns_mobile": "1",
        "swipe_on_mobile": true,
        "padding_bottom": 36
      }
    },
    "eac6855e-ae7f-4511-aeae-8e2b12d1451b": {
      "type": "rich-text",
      "blocks": {
        "d5a07f30-c0dc-43cf-9cfe-a87d802bd345": {
          "type": "custom_liquid",
          "settings": {
            "custom_liquid": "<style>\n    .acne-reviews{\n        font-family: 'Poppins';\n        margin: auto;\n            width: 74%;\n        text-align: left;height: fit-content;\n        border: 1px solid rgba(74, 74, 74, 0.5);\n    }\n    .ninety-seven {\n            width: 74%;\n        text-align: left;\n        margin: auto;\n        display: flex;\n        padding-top: 5%;\n    }\n    .percent {\n        padding: 0 5%;\n        color: #cc4e61;\n    }\n    .success-text {\n        border-left: 1px solid rgba(0, 0, 0, 0.16);\n        display: flex;\n        align-items: center;\n        padding: 0 5%\n    }\n    .legend-title {\n        margin: auto;\n        text-align: center;\n    }\n    .legend-title h4 {\n        font-size: 1.5rem;\n        color: #cc4e61;\n    }\n    .twenty-days {\n        margin: 0 42%;\n    }\n    .alisha-stars {\n        margin-top: -10%;\n        color: #FFCD4E;\n    }\n   .comments-text {\n       padding-top: 2%;\n   }\n   .customer {\n        display: flex;\n        flex-directopn: row;\n    }\n    .customer-name h1{\n        color: #cc4e61;\n    }\n    .comments {\n        padding: 0 5%;\n        display: flex;\n        justify-content: center;\n    }\n    .large-quotes {\n        font-size: 4rem;\n        margin-top: 0;\n        padding-right: 1.5rem;\n        color: #cc4e61;\n    }\n<\/style>\n<div>\n \n    <div class=\"ninety-seven\"     style=\"right: -160px;\n    position: relative;\n    top: 49px;\"\n>\n        <h1 class=\"percent\" style=\"font-family: 'Poppins';\nfont-style: normal;\nfont-weight: bold;\nfont-size: 45px;\nline-height: 54px;\n\/* identical to box height *\/\n\ntext-align: center;\n\ncolor: #CC4E61;\n\">+97%<\/h1>\n        <p class=\"success-text\" style=\"font-family: 'Poppins';\nfont-style: normal;\nfont-weight: 300;\nfont-size: 16px;\nline-height: 27px;\n\ncolor: #4A4A4A;\">\n            Success rate in all clinical trials within 28 days using<br>\nRecovery & Repair Gel.\n        <\/p>\n\n    <\/div>\n<\/div>"
          }
        }
      },
      "block_order": [
        "d5a07f30-c0dc-43cf-9cfe-a87d802bd345"
      ],
      "settings": {
        "text_alignment": "center",
        "mobile_text_alignment": "center",
        "horizontal_content": false,
        "narrow": false,
        "show_divider": false,
        "use_custom_colors": false,
        "colors_text": "#212326",
        "colors_background": "#ffffff",
        "gradient_background": "",
        "padding_top": 36,
        "padding_bottom": 36
      }
    },
    "1fee61a9-ef82-4918-92e3-2864e786840f": {
      "type": "pagefly-section",
      "blocks": {
        "3d212724-c289-4440-af6c-33fdee9298b1": {
          "type": "shopify:\/\/apps\/stamped-product-reviews-ugc\/blocks\/badge-ribbon-image\/a103faaf-2125-4b0e-89fa-de5149736723",
          "settings": {
            "api_key": "",
            "store_hash": "",
            "label1": "",
            "label2": "",
            "width": "",
            "height": ""
          }
        }
      },
      "block_order": [
        "3d212724-c289-4440-af6c-33fdee9298b1"
      ],
      "settings": {
        "section_id": "pf-50486ac9"
      }
    },
    "33215fec-c0c5-47ba-bded-74b23046fe26": {
      "type": "custom-liquid",
      "disabled": true,
      "settings": {
        "custom_liquid": "<html lang=\"en\">\n\n<head>\n  <meta charset=\"UTF-8\">\n  <title>CodePen - Ratings Stars Demo<\/title>\n  <link rel='stylesheet' href='https:\/\/cdnjs.cloudflare.com\/ajax\/libs\/font-awesome\/4.7.0\/css\/font-awesome.css'>\n  <link rel='stylesheet' href='https:\/\/maxcdn.bootstrapcdn.com\/bootstrap\/4.0.0-beta.3\/css\/bootstrap.min.css'>\n  <link rel=\"stylesheet\" href=\".\/style1.css\">\n  <script src=\"https:\/\/cdnjs.cloudflare.com\/ajax\/libs\/prefixfree\/1.0.7\/prefixfree.min.js\"><\/script>\n\n<\/head>\n\n<body>\n  \n <div class=\"container\"> \n    <div class=\"row\">\n      <div class=\"col-sm-12\"> \n        <div class=\"card\">\n          <div class=\"card-header\">Ratings Demo<\/div>\n          <div class=\"card-body\">\n            <div id=\"stars_rating\">\n              <p class=\"heading\">Please rate this title.<\/p>\n              <div class=\"stars\">\n                <div class=\"star\">★<\/div>\n                <div class=\"star\">★<\/div>\n                <div class=\"star\">★<\/div>\n                <div class=\"star\">★<\/div>\n                <div class=\"star\">★<\/div>\n              <\/div>\n              <p class=\"rates\"> <span class=\"avg\"> <\/span> | Your Rating: <span class=\"rate\"> <\/span><\/p>\n              <div class=\"customInput-wrap\">\n                <span class=\"count\">0<\/span><p>5<\/p><input class=\"progressbar\" id=\"5\" type=\"range\" name=\"rangeInput\" min=\"1\" max=\"100\" value=\"0\" >\n                <span class=\"count\">0<\/span><p>4<\/p><input class=\"progressbar\" id=\"4\" type=\"range\" name=\"rangeInput\" min=\"1\" max=\"100\" value=\"0\" \/>\n                <span class=\"count\">0<\/span><p>3<\/p><input class=\"progressbar\" id=\"3\" type=\"range\" name=\"rangeInput\" min=\"1\" max=\"100\" value=\"0\" \/>\n                <span class=\"count\">0<\/span><p>2<\/p><input class=\"progressbar\" id=\"2\" type=\"range\" name=\"rangeInput\" min=\"1\" max=\"100\" value=\"0\" \/>\n                <span class=\"count\">0<\/span><p>1<\/p><input class=\"progressbar\" id=\"1\" type=\"range\" name=\"rangeInput\" min=\"1\" max=\"100\" value=\"0\" \/>\n                <span class=\"count\">0<\/span><p>Total <\/p><p id=\"total\" >0<\/p>\n                <output>\n                  <style>\n                    .customInput-wrap {\n                      border: 1px solid red;\n                      position: relative;\n                    }\n\n                    input[type=\"range\"] {\n                      width: 100%;\n                    }\n\n                    output {\n                      border: 1px solid blue;\n                      position: absolute;\n                      left: 50%;\n                      transform: translateX(-50%);\n                    }\n                  <\/style>\n                <\/output>\n              <\/div>\n            <\/div>\n\n          <\/div>\n          \n        <\/div>\n      <\/div>\n    <\/div>\n  <\/div> \n\n  <script src='https:\/\/code.jquery.com\/jquery-3.2.1.slim.min.js'><\/script>\n  <script src='https:\/\/cdnjs.cloudflare.com\/ajax\/libs\/popper.js\/1.12.9\/umd\/popper.min.js'><\/script>\n  <script src='https:\/\/maxcdn.bootstrapcdn.com\/bootstrap\/4.0.0-beta.3\/js\/bootstrap.min.js'><\/script>\n  <script src=\".\/script1.js\"><\/script>\n\n<\/body>\n\n<\/html> \n<html lang=\"en\" >\n<head>\n   <meta charset=\"UTF-8\">\n  <title>Customer Review<\/title>\n  <link rel=\"stylesheet\" href=\"https:\/\/cdnjs.cloudflare.com\/ajax\/libs\/meyer-reset\/2.0\/reset.min.css\">\n<link rel='stylesheet' href='https:\/\/maxcdn.bootstrapcdn.com\/font-awesome\/4.6.0\/css\/font-awesome.min.css'>\n<link rel='stylesheet' href='https:\/\/maxcdn.bootstrapcdn.com\/bootstrap\/3.3.6\/css\/bootstrap.min.css'><link rel=\"stylesheet\" href=\".\/style.css\">\n\n<\/head>\n<style>\n  @import 'https:\/\/fonts.googleapis.com\/css?family=Montserrat';\nhtml, body {\n  height: 100%;\n  width: 100%;\n  background-color: #334;\n  overflow: hidden;\n  color: white;\n  font-family: \"Montserrat\", sans-serif;\n}\n\n.fb-form {\n  width: 300px;\n  top: 50%;\n  left: 50%;\n  position: relative;\n  transform: translateY(-50%) translateX(-50%);\n}\n.fb-form h2 {\n  text-align: center;\n  font-size: 1.4em;\n}\n.fb-form input {\n  margin: 15px 0;\n}\n.fb-form input[type=submit] {\n  margin-top: 0;\n}\n.fb-form textarea {\n  height: 100px;\n}\n\n.rating {\n  margin: 15px auto;\n  transform: rotateY(180deg);\n  width: 100%;\n}\n.rating .fa-star {\n  font-size: 2em;\n  cursor: pointer;\n  margin: 0 5.1%;\n  transition: all 0.5s ease;\n}\n.rating .fa-star.active-rating {\n  transition: all 0.5s ease;\n  -webkit-animation: rating-highlight 0.5s ease forwards;\n          animation: rating-highlight 0.5s ease forwards;\n}\n.rating .fa-star.active-rating:nth-child(5) {\n  color: yellow;\n  transition: all 0.5s ease;\n}\n.rating .fa-star.active-rating:nth-child(1) {\n  color: yellow;\n  transition: all 0.5s ease;\n}\n.rating .fa-star.active-rating:nth-child(1) ~ .fa-star {\n  transition: all 0.5s ease;\n  color: yellow;\n}\n.rating .fa-star.active-rating:nth-child(2) {\n  color: yellow;\n  transition: all 0.5s ease;\n}\n.rating .fa-star.active-rating:nth-child(2) ~ .fa-star {\n  transition: all 0.5s ease;\n  color: yellow;\n}\n.rating .fa-star.active-rating:nth-child(3) {\n  color: yellow;\n  transition: all 0.5s ease;\n}\n.rating .fa-star.active-rating:nth-child(3) ~ .fa-star {\n  transition: all 0.5s ease;\n  color: yellow;\n}\n.rating .fa-star.active-rating:nth-child(4) {\n  color: yellow;\n  transition: all 0.5s ease;\n}\n.rating .fa-star.active-rating:nth-child(4) ~ .fa-star {\n  transition: all 0.5s ease;\n  color: yellow;\n}\n.rating .fa-star:hover:nth-child(5) {\n  color: yellow;\n  transition: all 0.5s ease;\n}\n.rating .fa-star:hover:nth-child(1) {\n  color: yellow;\n  transition: all 0.5s ease;\n}\n.rating .fa-star:hover:nth-child(1) ~ .fa-star {\n  color: yellow;\n  transition: all 0.5s ease;\n}\n.rating .fa-star:hover:nth-child(2) {\n  color: yellow;\n  transition: all 0.5s ease;\n}\n.rating .fa-star:hover:nth-child(2) ~ .fa-star {\n  color: yellow;\n  transition: all 0.5s ease;\n}\n.rating .fa-star:hover:nth-child(3) {\n  color: yellow;\n  transition: all 0.5s ease;\n}\n.rating .fa-star:hover:nth-child(3) ~ .fa-star {\n  color: yellow;\n  transition: all 0.5s ease;\n}\n.rating .fa-star:hover:nth-child(4) {\n  color: yellow;\n  transition: all 0.5s ease;\n}\n.rating .fa-star:hover:nth-child(4) ~ .fa-star {\n  color: yellow;\n  transition: all 0.5s ease;\n}\n\n@-webkit-keyframes rating-highlight {\n  0% {\n    transform: rotate(-10deg) scale(1.2);\n  }\n  20% {\n    transform: rotate(10deg) scale(0.8);\n  }\n  50% {\n    transform: rotate(-5deg) scale(1.1);\n  }\n  80% {\n    transform: rotate(5deg) scale(0.9);\n  }\n  100% {\n    transform: rotate(0deg) scale(1);\n  }\n}\n\n@keyframes rating-highlight {\n  0% {\n    transform: rotate(-10deg) scale(1.2);\n  }\n  20% {\n    transform: rotate(10deg) scale(0.8);\n  }\n  50% {\n    transform: rotate(-5deg) scale(1.1);\n  }\n  80% {\n    transform: rotate(5deg) scale(0.9);\n  }\n  100% {\n    transform: rotate(0deg) scale(1);\n  }\n}\n\n<\/style>\n<body>\n<div class='fb-form'>\n  <form action='#' class='form-group'>\n    <h2>Customer Review<\/h2>\n    <input class='form-control' placeholder='Name' type='text'>\n    <input class='form-control' placeholder='Email' type='text'>\n    <textarea class='form-control' id='fb-comment' name='' placeholder='Thanks for Reviews'><\/textarea>\n    <div class='rating'>\n      <i class='fa fa-star'><\/i>\n      <i class='fa fa-star'><\/i>\n      <i class='fa fa-star'><\/i>\n      <i class='fa fa-star'><\/i>\n      <i class='fa fa-star'><\/i>\n    <\/div>\n    <input class='form-control btn btn-primary' type='submit'>\n  <\/form>\n<\/div>\n <script src='https:\/\/code.jquery.com\/jquery-2.2.4.min.js'><\/script><script  src=\".\/script.js\"><\/script>\n\n<\/body>\n<\/html>",
        "full_width": false,
        "show_divider": false,
        "padding_top": 36,
        "columns_mobile": "1",
        "swipe_on_mobile": true,
        "padding_bottom": 36
      }
    },
    "85338335-2df9-4891-9265-47d749cb0dff": {
      "type": "custom-liquid",
      "disabled": true,
      "settings": {
        "custom_liquid": "<br>\n<head>\n<meta name=\"viewport\" content=\"width=device-width, initial-scale=1\">\n<style>\n* {\n  box-sizing: border-box;\n}\n\n\n.sec {\n  float: left;\n  width: 28%;\n  padding: 10px;\n  height: 300px; \n  position:relative;\n  top:217px;\nleft:-355px;\n}\n\n.carbon_main:after {\n  content: \"\";\n  display: table;\n  clear: both;\n\n}\n.carbon_main:after {\n  content: \"\";\n  display: table;\n  clear: both;\n\n}\n\n.alisha-customer-acne_slider {\n        margin: 60px auto;\n        max-width: 1200px;\n      }\n      .alisha-customer-acne_slider {\n        flex: 1 1 0;\n      }\n\n      .inner {\n        padding: 6px;\n      }\n\n      img {\n        width: 100%;\n        height: auto;\n      }\n      \/* img:hover {\n        opacity: 0.9;\n      } *\/\n\n      .ba-slider {\n    position: relative;\n    overflow: hidden;\n  \n  }\n  \n  .ba-slider img {\n    width: 100%;\n    height: 100%;\n    display:block;\n  }\n  \n  .ba-slider .resize {\n    position: absolute;\n    top:0;\n    left: 0;\n    height: 100%;\n    width: 50%;\n    overflow: hidden;\n  }\n  \n  .handle {\n    position:absolute; \n    left:50%;\n    top:0;\n    bottom:0;\n    width:4px;\n    margin-left:-2px;\n  \n    background: #FFFFFF;\n    cursor: ew-resize;\n  }\n  \n  .handle:after {\n      position: absolute;\n      top: 50%;\n      width: 68px;\n      height: 67px;\n      margin: -32px 0 0 -32px;\n  \n      \/* content:'\\21d4'; *\/\n      content:url('https:\/\/cdn.shopify.com\/s\/files\/1\/0669\/6343\/9927\/files\/Vector_15.png?v=1669018900');\n      color:#CC4E61;\n      font-weight:bold;\n      font-size:36px;\n      text-align:center;\n      line-height:64px;\n    \/* background-image:url(.\/Group\\ 928.png); *\/\n      background: #FFFFFF; \n      border:3px solid #FFFFFF; \/* darken(@orange, 5%) *\/\n      border-radius: 50%;\n      transition:all 0.3s ease;\n      box-shadow:\n        0 2px 6px rgba(0,0,0,.3), \n        inset 0 2px 0 rgba(255,255,255,.5),\n        inset 0 60px 50px -30px #FFFFFF; \/* lighten(@orange, 20%)*\/ \n  }\n  \n  .handle.draggable:after {\n      width: 68px;\n      height: 67px;\n      margin: -32px 0 0 -32px;\n      line-height:50px;\n      font-size:30px;\n  }\n  .dev .slick-list\n{\n    position: absolute;\n\n    display: block;\n    overflow: hidden;\n\n    margin: 0;\n    padding: 0;\n}\n.one-slider{\n    \/* display:flex; *\/\n    flex-direction: column;\n}\n\n.img_content{\n    flex-direction: column;\n}\n.title {\n        text-align: center;\n        margin-top: 60px;\n        font-family: 'Poppins';\n        font-style: normal;\n        font-weight: 600;\n        font-size: 40px;\n        line-height: 60px;\n        text-align: center;\n        color: #CC4E61;\n      }\n\n@media screen and (max-width: 600px) {\n  .sec {\n    width: 100%;\n    height: 100%;\n  }\n}\n<\/style>\n<\/head>\n<body>\n\n\n<div class=\"carbon_main1\">\n   <div class=\"sec\" >\n    <div class=\"one-slider\">\n        <div class=\"ba-slider\" style=\"position: absolute;left: 500px;width: 463px;top:-118px;\">\n\n            <img src=\"https:\/\/cdn.shopify.com\/s\/files\/1\/0669\/6343\/9927\/files\/comp1.png?v=1671687916\">\n            <div class=\"resize\">\n                <img src=\"https:\/\/cdn.shopify.com\/s\/files\/1\/0669\/6343\/9927\/files\/comp2.png?v=1671687916\">\n            <\/div>\n            <span class=\"handle\"><\/span>\n         <\/div>\n         <br\/>\n         <br\/>\n                  <div style=\"position:absolute;right: -644px; top: 280px;width: 467px;\"> \n                    <button  href=\"https:\/\/seacra-dev.myshopify.com\/pages\/janes-story\" style=\"color:#cc4e61;\">Listen to Jane’s Story<\/button>\n                  <\/div>\n    <\/div>\n  <\/div>\n\n <\/div>\n\n<\/div>\n<div class=\"carbon_main2\">\n    <div class=\"sec\" >\n     <div class=\"one-slider\">\n         <div class=\"ba-slider\" style=\"position: absolute;left: 500px;width: 463px;top:-118px;\">\n \n             <img src=\"https:\/\/cdn.shopify.com\/s\/files\/1\/0669\/6343\/9927\/files\/comp3.png?v=1671687918\">\n             <div class=\"resize\">\n                 <img src=\"https:\/\/cdn.shopify.com\/s\/files\/1\/0669\/6343\/9927\/files\/comp4.png?v=1671687917\">\n             <\/div>\n             <span class=\"handle\"><\/span>\n          <\/div>\n          <br\/>\n          <br\/>\n                   <div style=\"position:absolute;right: -669px; top: 280px;width: 467px;\"> \n                     <button  href=\"https:\/\/seacra-dev.myshopify.com\/pages\/janes-story\" style=\"color:#cc4e61;\">Listen to Maddy’s Story<\/button>\n                   <\/div>\n     <\/div>\n   <\/div>\n \n  <\/div>\n \n <\/div>\n <div class=\"carbon_main3\">\n    <div class=\"sec\" >\n     <div class=\"one-slider\">\n         <div class=\"ba-slider\" style=\"position: absolute;left: 500px;width: 463px;top:-118px;\">\n \n             <img src=\"https:\/\/cdn.shopify.com\/s\/files\/1\/0669\/6343\/9927\/files\/MicrosoftTeams-image7dfb42950efb84556e517c8ba692901dec171e12f472534be966fc20efa9636e_1_2.jpg?v=1669781939\">\n             <div class=\"resize\">\n                 <img src=\"https:\/\/cdn.shopify.com\/s\/files\/1\/0669\/6343\/9927\/files\/MicrosoftTeams-image623588dac018a0fe847b2e0a282fe12009d6fd938b9982860dd37da31ce54811_1_2.jpg?v=1669781935\">\n             <\/div>\n             <span class=\"handle\"><\/span>\n          <\/div>\n          <br\/>\n          <br\/>\n                   <div style=\"position:absolute;right: -652px; top: 280px;width: 467px;\"> \n                     <button  href=\"https:\/\/seacra-dev.myshopify.com\/pages\/janes-story\" style=\"color:#cc4e61;\">Listen to Alisha’s Story<\/button>\n                   <\/div>\n     <\/div>\n   <\/div>\n \n  <\/div>\n \n <\/div>\n\n<\/body>\n\n<script src=\"https:\/\/cdnjs.cloudflare.com\/ajax\/libs\/jquery\/2.1.3\/jquery.min.js\"><\/script>\n<script>\n\n      $(document).ready(function(){\n          $('.ba-slider').each(function(){\n            var cur = $(this);\n            var width = cur.width()+'px';\n            cur.find('.resize img').css('width', width);\n            drags(cur.find('.handle'), cur.find('.resize'), cur);\n          });\n        });\n        $(window).resize(function(){\n          $('.ba-slider').each(function(){\n            var cur = $(this);\n            var width = cur.width()+'px';\n            cur.find('.resize img').css('width', width);\n          });\n        });\n\n        function drags(dragElement, resizeElement, container) {\n          dragElement.on('mousedown touchstart', function(e) {\n            \n            dragElement.addClass('draggable');\n            resizeElement.addClass('resizable');\n            var startX = (e.pageX) ? e.pageX : e.originalEvent.touches[0].pageX;\n            var dragWidth = dragElement.outerWidth(),\n            posX = dragElement.offset().left + dragWidth - startX,\n            containerOffset = container.offset().left,\n            containerWidth = container.outerWidth();\n            minLeft = containerOffset + 10;\n            maxLeft = containerOffset + containerWidth - dragWidth - 10;\n            dragElement.parents().on(\"mousemove touchmove\", function(e) {\n              var moveX = (e.pageX) ? e.pageX : e.originalEvent.touches[0].pageX;\n              console.log(startX, e.pageX);\n              leftValue = moveX + posX - dragWidth;\n              if ( leftValue < minLeft) {\n                leftValue = minLeft;\n              } else if (leftValue > maxLeft) {\n                leftValue = maxLeft;\n              }\n              widthValue = (leftValue + dragWidth\/2 - containerOffset)*100\/containerWidth+'%';\n              $('.draggable').css('left', widthValue).on('mouseup touchend touchcancel', function () {\n                $(this).removeClass('draggable');\n                resizeElement.removeClass('resizable');\n              });\n              $('.resizable').css('width', widthValue);\n            }).on('mouseup touchend touchcancel', function(){\n              dragElement.removeClass('draggable');\n              resizeElement.removeClass('resizable');\n            });\n            e.preventDefault();\n          }).on('mouseup touchend touchcancel', function(e){\n            dragElement.removeClass('draggable');\n            resizeElement.removeClass('resizable');\n          });\n        }\n    <\/script>",
        "full_width": false,
        "show_divider": false,
        "padding_top": 36,
        "columns_mobile": "1",
        "swipe_on_mobile": true,
        "padding_bottom": 36
      }
    },
    "23ad6690-908e-494d-8f26-c4eb571f6962": {
      "type": "customer-review-section",
      "settings": {
      }
    },
    "30d21ac0-909f-4e7f-aad4-f17ae379f94c": {
      "type": "clinictrial",
      "disabled": true,
      "settings": {
      }
    },
    "6d847e60-da1e-4358-bbd1-32444cbb490a": {
      "type": "custom-liquid",
      "settings": {
        "custom_liquid": "<style>\n  .clinical {\n      width: 100%;\n      text-align: center;\n      border-bottom: 1px\n      solid #cc4e61;\n      line-height: 1px;\n      margin: 10px 0 20px;\n      font-weight: 600;\n      font-size: 24px;\n   }\n   .clinical .trial {\n       background:#fff;\n       padding:0 calc(0.5em + 1.25vmin);\n   }\n  <\/style>\n  <div>\n    <h3 class=\"clinical\"><span class=\"trial\" style=\"color:#cc4e61;\">Clinical Trial<\/span><\/h3>\n  <\/div>",
        "full_width": true,
        "show_divider": false,
        "padding_top": 36,
        "columns_mobile": "1",
        "swipe_on_mobile": true,
        "padding_bottom": 36
      }
    },
    "a3a066ac-5e9b-4351-b1de-f91bea1a8c51": {
      "type": "rich-text",
      "blocks": {
        "4e6004a6-143d-475f-a4ef-310928eb0ce1": {
          "type": "custom_liquid",
          "settings": {
            "custom_liquid": "<span style=\"font-family: 'Poppins';\nfont-style: normal;\nfont-weight: 500;\nfont-size: 18px;\nline-height: 36px;\ntext-align: center;\n\ncolor: #4A4A4A;\">The results from our 28-day clinical trial to understand the instrumental efficacy for the evaluation of <br>the cosmetic product seacra recovery and repair gel.<\/span><div>"
          }
        }
      },
      "block_order": [
        "4e6004a6-143d-475f-a4ef-310928eb0ce1"
      ],
      "settings": {
        "text_alignment": "center",
        "mobile_text_alignment": "center",
        "horizontal_content": false,
        "narrow": false,
        "show_divider": false,
        "use_custom_colors": false,
        "colors_text": "#212326",
        "colors_background": "#ffffff",
        "gradient_background": "",
        "padding_top": 0,
        "padding_bottom": 36
      }
    },
    "c2c213a2-6f28-4b8e-af65-fe8235b53daa": {
      "type": "gallery",
      "blocks": {
        "template--17280886735159__c2c213a2-6f28-4b8e-af65-fe8235b53daa-1671612674c18711d2-0": {
          "type": "image",
          "settings": {
            "image": "shopify:\/\/shop_images\/Group_1473.png",
            "image_position": "center center",
            "subheading": "",
            "subheading_size": "h5",
            "heading": "",
            "heading_size": "h3",
            "link": "",
            "text_box_position": "middle-center"
          }
        },
        "template--17280886735159__c2c213a2-6f28-4b8e-af65-fe8235b53daa-1671612674c18711d2-1": {
          "type": "image",
          "settings": {
            "image": "shopify:\/\/shop_images\/Group_1468.png",
            "image_position": "center center",
            "subheading": "",
            "subheading_size": "h5",
            "heading": "",
            "heading_size": "h3",
            "link": "",
            "text_box_position": "middle-center"
          }
        },
        "template--17280886735159__c2c213a2-6f28-4b8e-af65-fe8235b53daa-1671612674c18711d2-2": {
          "type": "image",
          "settings": {
            "image": "shopify:\/\/shop_images\/Group_1470.png",
            "image_position": "center center",
            "subheading": "",
            "subheading_size": "h5",
            "heading": "",
            "heading_size": "h3",
            "link": "",
            "text_box_position": "middle-center"
          }
        }
      },
      "block_order": [
        "template--17280886735159__c2c213a2-6f28-4b8e-af65-fe8235b53daa-1671612674c18711d2-0",
        "template--17280886735159__c2c213a2-6f28-4b8e-af65-fe8235b53daa-1671612674c18711d2-1",
        "template--17280886735159__c2c213a2-6f28-4b8e-af65-fe8235b53daa-1671612674c18711d2-2"
      ],
      "settings": {
        "per_row": 4,
        "spacing_images": 12,
        "image_height": 490,
        "apply_overlay": true,
        "full_width": false,
        "show_divider": false,
        "heading": "",
        "heading_size": "h1",
        "heading_alignment": "left",
        "heading_tag": "h2",
        "columns_mobile": "1",
        "swipe_on_mobile": true,
        "mobile_image_height": 160,
        "padding_top": 36,
        "padding_bottom": 36
      }
    },
    "d9bb16de-fbab-4021-9002-0e6fde58c088": {
      "type": "custom-liquid",
      "disabled": true,
      "settings": {
        "custom_liquid": "<link rel='stylesheet' href='https:\/\/cdnjs.cloudflare.com\/ajax\/libs\/twitter-bootstrap\/3.3.7\/css\/bootstrap.min.css'>\n  <style>\n    .image-container12 {\n      padding-bottom: 50px;}.row {\n      padding-top: 50px;\n    }\n    .image-text-overlay {\n      width: 100%;\n      height: 80vh;\n      background-size: cover;\n      background-repeat: no-repeat;\n      position: relative;\n    }\n    .image-text-overlay.text-white {\n      color: white;\n    }\n    .image-text-overlay .overlay-title {\n      font-size: 27px;\n      text-transform: uppercase;\n    }\n    .image-text-overlay .overlay-subtext {\n      font-size: 20px;\n    }\n    .image-text-overlay .overlay-white,\n    .image-text-overlay .overlay-black {\n      position: absolute;\n      left: 0;\n      top: 0;\n      right: 0;\n      bottom: 0;\n      z-index: 1;\n      opacity: 0.7;\n    }\n    .image-text-overlay .overlay-black {\n      background: transparent;\n    }\n    .image-text-overlay .overlay-white {\n      background: #fff;\n    }\n    .text-top-left,\n    .text-top-center,\n    .text-top-right,\n    .text-middle-left,\n    .text-middle-center,\n    .text-middle-right,\n    .text-bottom-left,\n    .text-bottom-right,\n    .text-bottom-center {\n      display: table;\n    }\n    .text-top-left p,\n    .text-top-center p,\n    .text-top-right p,\n    .text-middle-left p,\n    .text-middle-center p,\n    .text-middle-right p,\n    .text-bottom-left p,\n    .text-bottom-right p,\n    .text-bottom-center p {\n      display: table-cell;\n      position: relative;\n      z-index: 2;\n      padding: 15px 20px 15px 20px;\n    }\n    .text-top-left p {\n      vertical-align: top;\n      text-align: left;\n    }\n    .text-top-center p {\n      vertical-align: top;\n      text-align: center;\n    }\n    .text-top-right p {\n      vertical-align: top;\n      text-align: right;\n    }\n    .text-middle-left p {\n      vertical-align: middle;\n      text-align: left;\n    }\n    .text-middle-center p {\n      vertical-align: middle;\n      text-align: center;\n    }\n    .text-middle-right p {\n      vertical-align: middle;\n      text-align: right;\n    }\n    .text-bottom-left p {\n      vertical-align: bottom;\n      text-align: left;\n    }\n    .text-bottom-center p {\n      vertical-align: bottom;\n      text-align: center;\n    }\n    .text-bottom-right p {\n      vertical-align: bottom;\n      text-align: right;\n    }\n    @media (min-width: 1200px) {\n      .container {\n        width: 1200px;\n      }\n    }\n    @media screen and (max-width: 992px) {\n      .col-md-4 {\n        padding-bottom: 25px;\n      }\n    }\n  <\/style>\n  \n  <div class=\"image-container12\" >  \n    <div class=\"row\">\n      <div class=\"col-md-4 col-xs-12\">\n        <div class=\"image-text-overlay text-bottom-center text-white\" style=\"background-image: url(https:\/\/cdn.shopify.com\/s\/files\/1\/0669\/6343\/9927\/files\/Mask_group_5_6bd7956d-15fd-4a37-92cc-ee4fd38197fc.png?v=1670655412);height:51vh;\">        \n          <p>\n            <span class=\"overlay-title\">100%<\/span><br>\n            <span class=\"overlay\">Agreed that their skin was more<\/span><br>\n            <span class=\"overlay-subtext\">Hydrated<\/span>\n          <\/p>\n          <div class=\"overlay-black\"><\/div>       \n        <\/div>\n      <\/div>\n          <div class=\"col-md-4 col-xs-12\">\n        <div class=\"image-text-overlay text-bottom-center text-white\" style=\"background-image: url(https:\/\/cdn.shopify.com\/s\/files\/1\/0669\/6343\/9927\/files\/Mask_group_29.jpg?v=1670395844);height:51vh;\">        \n          <p>\n            <span class=\"overlay-title\">95%<\/span><br>\n            <span class=\"overlay\">Agreed that their visible bumps & blemishes<\/span><br>\n            <span class=\"overlay-subtext\">had Faded<\/span>\n          <\/p>\n          <div class=\"overlay-black\"><\/div>       \n        <\/div>\n      <\/div>\n         <div class=\"col-md-4 col-xs-12\">\n        <div class=\"image-text-overlay text-bottom-center text-white\" style=\"background-image: url(https:\/\/cdn.shopify.com\/s\/files\/1\/0669\/6343\/9927\/files\/Mask_group_28.jpg?v=1670395841);height:51vh;\">        \n          <p>\n            <span class=\"overlay-title\">90%<\/span><br>\n            <span class=\"overlay\">Agreed that their skin became<\/span><br>\n            <span class=\"overlay-subtext\">Brighter<\/span>\n          <\/p>\n          <div class=\"overlay-black\"><\/div>       \n        <\/div>\n      <\/div>\n  <\/div>",
        "full_width": false,
        "show_divider": false,
        "padding_top": 36,
        "columns_mobile": "1",
        "swipe_on_mobile": true,
        "padding_bottom": 36
      }
    },
    "c946058e-acd6-4195-b87e-3c0e0c963562": {
      "type": "rich-text",
      "disabled": true,
      "blocks": {
        "53780dcd-ccf1-4df6-9ff1-8c8325808de0": {
          "type": "custom_liquid",
          "settings": {
            "custom_liquid": "<style>\n  \n  .section-1{\n    display: flex;\n    align-items: center; \n    flex-wrap: wrap;\n    justify-content: center;\n  }\n  .Redness_text {\n    display: flex;\n    border: 0px solid;\n    align-items: center; \n    flex-wrap: wrap;\n    justify-content: center;\n  }\n  .Redness_image, .Redness_graph {\n    display: flex;\n    border: 0px solid;\n    justify-content: center;\n  }\n  <\/style>\n  <div class=\"section-1\">\n    <h1 style=\"border: 1px solid #4a4a4a;color:#cc4e61;text-align: center;width:626px;height:62px;display:flex;justify-content:center;align-items:center;\">Redness Reduced by 20% over the 28 days<\/h1>\n  <div class=\"Redness_text\" style=\"column-gap: 232px;\">\n    <div class=\"Redness_image\" style=\"width:404px;\">\n      <img src=\"https:\/\/cdn.shopify.com\/s\/files\/1\/0669\/6343\/9927\/files\/1a.png?v=1670854192\" \/>\n    <\/div>\n    <div class=\"Redness_graph\" style=\"right: -8px;\n    position: relative;\n    width: 407px;\n\">\n          <img src=\"https:\/\/cdn.shopify.com\/s\/files\/1\/0669\/6343\/9927\/files\/2b1.png?v=1670854203\" \/>\n    <\/div>\n  <\/div>"
          }
        }
      },
      "block_order": [
        "53780dcd-ccf1-4df6-9ff1-8c8325808de0"
      ],
      "settings": {
        "text_alignment": "center",
        "mobile_text_alignment": "center",
        "horizontal_content": false,
        "narrow": false,
        "show_divider": false,
        "use_custom_colors": false,
        "colors_text": "#212326",
        "colors_background": "#ffffff",
        "gradient_background": "",
        "padding_top": 36,
        "padding_bottom": 36
      }
    },
    "d985bae6-46b4-4388-a1da-418c6b764aff": {
      "type": "rich-text",
      "disabled": true,
      "blocks": {
        "cdbd5f1a-29e2-474b-bf56-21041b614850": {
          "type": "custom_liquid",
          "disabled": true,
          "settings": {
            "custom_liquid": "<style>\n  \n  .section-1{\n    display: flex;\n    align-items: center; \n    flex-wrap: wrap;\n    justify-content: center;\n  }\n  .hydration_text {\n    display: flex;\n    border: 0px solid;\n    align-items: center; \n    flex-wrap: wrap;\n    justify-content: center;\n  }\n  .hydration_image, .hydration_graph {\n    display: flex;\n    border: 0px solid;\n    justify-content: center;\n  }\n  <\/style>\n  <div class=\"section-1\">\n    <h1 style=\"border: 1px solid #4a4a4a;width:614px;color:#cc4e61;text-align: center;align:center;width:646px;height:61px;display:flex;justify-content:center;align-items:center;\";>Hydration Increased by 17% over the 28 days<\/h1>\n  <div class=\"hydration_text\" style=\"column-gap: 232px;\">\n    <div class=\"hydration_image\" style=\"width:440px;\">\n      <img src=\"https:\/\/cdn.shopify.com\/s\/files\/1\/0669\/6343\/9927\/files\/Untitled2.png?v=1671446707\" \/>\n    <\/div>\n    <div class=\"hydration_graph\" style=\"right: -5px;\n    position: relative;\n    width: 352px;\n\">\n          <img src=\"https:\/\/cdn.shopify.com\/s\/files\/1\/0669\/6343\/9927\/files\/1b.png?v=1670854196\" \/>\n    <\/div>\n  <\/div>"
          }
        }
      },
      "block_order": [
        "cdbd5f1a-29e2-474b-bf56-21041b614850"
      ],
      "settings": {
        "text_alignment": "center",
        "mobile_text_alignment": "center",
        "horizontal_content": false,
        "narrow": false,
        "show_divider": false,
        "use_custom_colors": false,
        "colors_text": "#212326",
        "colors_background": "#ffffff",
        "gradient_background": "",
        "padding_top": 36,
        "padding_bottom": 36
      }
    },
    "b64310b3-30c8-48fe-8a6f-c1e08770a4cb": {
      "type": "image-banner",
      "settings": {
        "image": "shopify:\/\/shop_images\/Group_1218_2_bb9ff6da-2566-402c-9804-24aa62fe2fd1.jpg",
        "image_position": "center center",
        "text_box_position": "bottom-center",
        "text_alignment": "center",
        "image_ratio": "adapt",
        "show_text_box": false,
        "full_width": true,
        "show_divider": false,
        "mobile_text_alignment": "center",
        "mobile_image_ratio": "auto",
        "stack_images_on_mobile": true,
        "show_text_below": true,
        "colors_text": "#ffffff",
        "colors_overlay": "#000000",
        "colors_overlay_opacity": 0,
        "padding_top": 36,
        "padding_bottom": 36
      }
    },
    "0b5bef68-e699-4c2d-ae92-5c1914cdbaf8": {
      "type": "custom-liquid",
      "disabled": true,
      "settings": {
        "custom_liquid": "<style>\n  .heading-cust-3 {\n      width: 100%;\n      text-align: center;\n      border-bottom: 6px\n      solid #cc4e61;\n      line-height: 3px;\n      margin: 10px 0 20px;\n      font-weight: 600;\n      font-size: calc(1.25em + 0.25vmin);\n   }\n   .heading-cust-3 .spanned-cust-3 {\n       background:#fff;\n       padding:0 calc(0.5em + 1.25vmin);\n   }\n  <\/style>\n  <div>\n    <h3 class=\"heading-cust-3\"><span class=\"spanned-cust-3\">Subjective Questionnaire<\/span><\/h3>\n  <\/div>",
        "full_width": true,
        "show_divider": false,
        "padding_top": 0,
        "columns_mobile": "1",
        "swipe_on_mobile": true,
        "padding_bottom": 68
      }
    },
    "1df286e7-05fe-4cbb-9800-10e5d96bd8a5": {
      "type": "graph-slider",
      "disabled": true,
      "settings": {
      }
    },
    "search": {
      "type": "main-search",
      "disabled": true,
      "settings": {
        "products_per_row": 4,
        "rows_per_page": 9,
        "columns_mobile": "2",
        "pagination": "paginated",
        "enable_sticky_facet": true,
        "enable_sorting": true,
        "enable_viewing": true,
        "enable_filtering": true,
        "filter_type": "vertical",
        "enable_filtering_color_swatches": true,
        "filtering_color_swatches_add_label": false,
        "filtering_max_items": 6,
        "image_ratio": "portrait",
        "image_position": "center center",
        "enable_image_fill": true,
        "show_secondary_image": true,
        "show_vendor": true,
        "show_rating": true,
        "show_quick_buy": true,
        "enable_quick_view": true,
        "enable_color_swatches": true,
        "enable_countdown": true,
        "article_show_date": true,
        "article_show_author": false,
        "article_show_comment_count": true,
        "padding_top": 36,
        "padding_bottom": 60
      }
    },
    "4b708fd7-2e75-49e6-8353-6b28c5ab171f": {
      "type": "custom-liquid",
      "disabled": true,
      "settings": {
        "custom_liquid": "<!DOCTYPE html>\n<html lang=\"en\">\n\n<head>\n  <meta charset=\"UTF-8\">\n  <title>CodePen - Ratings Stars Demo<\/title>\n  <link rel='stylesheet' href='https:\/\/cdnjs.cloudflare.com\/ajax\/libs\/font-awesome\/4.7.0\/css\/font-awesome.css'>\n  <link rel='stylesheet' href='https:\/\/maxcdn.bootstrapcdn.com\/bootstrap\/4.0.0-beta.3\/css\/bootstrap.min.css'>\n  <link rel=\"stylesheet\" href=\".\/style.css\">\n  <script src=\"https:\/\/cdnjs.cloudflare.com\/ajax\/libs\/prefixfree\/1.0.7\/prefixfree.min.js\"><\/script>\n\n<\/head>\n\n<body>\n  <!-- partial:index.partial.html -->\n  <div class=\"container\">\n    <div class=\"row\">\n      <div class=\"col-sm-12\">\n        <div class=\"card\">\n          <div class=\"card-header\">Ratings Demo<\/div>\n          <div class=\"card-body\">\n            <div id=\"stars_rating\">\n              <p class=\"heading\">Please rate this title.<\/p>\n              <div class=\"stars\">\n                <div class=\"star\">★<\/div>\n                <div class=\"star\">★<\/div>\n                <div class=\"star\">★<\/div>\n                <div class=\"star\">★<\/div>\n                <div class=\"star\">★<\/div>\n              <\/div>\n              <p class=\"rates\"> <span class=\"avg\"> <\/span> | Your Rating: <span class=\"rate\"> <\/span><\/p>\n              <div class=\"customInput-wrap\">\n                <span class=\"count\">0<\/span><p>5<\/p><input class=\"progressbar\" id=\"5\" type=\"range\" name=\"rangeInput\" min=\"1\" max=\"100\" value=\"0\" >\n                <span class=\"count\">0<\/span><p>4<\/p><input class=\"progressbar\" id=\"4\" type=\"range\" name=\"rangeInput\" min=\"1\" max=\"100\" value=\"0\" \/>\n                <span class=\"count\">0<\/span><p>3<\/p><input class=\"progressbar\" id=\"3\" type=\"range\" name=\"rangeInput\" min=\"1\" max=\"100\" value=\"0\" \/>\n                <span class=\"count\">0<\/span><p>2<\/p><input class=\"progressbar\" id=\"2\" type=\"range\" name=\"rangeInput\" min=\"1\" max=\"100\" value=\"0\" \/>\n                <span class=\"count\">0<\/span><p>1<\/p><input class=\"progressbar\" id=\"1\" type=\"range\" name=\"rangeInput\" min=\"1\" max=\"100\" value=\"0\" \/>\n                <span class=\"count\">0<\/span><p>Total <\/p><p id=\"total\" >0<\/p>\n                <output>\n                  <style>\n                    .customInput-wrap {\n                      border: 1px solid red;\n                      position: relative;\n                    }\n\n                    input[type=\"range\"] {\n                      width: 100%;\n                    }\n\n                    output {\n                      border: 1px solid blue;\n                      position: absolute;\n                      left: 50%;\n                      transform: translateX(-50%);\n                    }\n                  <\/style>\n                <\/output>\n              <\/div>\n            <\/div>\n\n          <\/div>\n          \n        <\/div>\n      <\/div>\n    <\/div>\n  <\/div>\n  <!-- partial -->\n  <script src='https:\/\/code.jquery.com\/jquery-3.2.1.slim.min.js'><\/script>\n  <script src='https:\/\/cdnjs.cloudflare.com\/ajax\/libs\/popper.js\/1.12.9\/umd\/popper.min.js'><\/script>\n  <script src='https:\/\/maxcdn.bootstrapcdn.com\/bootstrap\/4.0.0-beta.3\/js\/bootstrap.min.js'><\/script>\n  <script src=\".\/script.js\"><\/script>\n\n<\/body>\n\n<\/html>",
        "full_width": false,
        "show_divider": false,
        "padding_top": 36,
        "columns_mobile": "1",
        "swipe_on_mobile": true,
        "padding_bottom": 36
      }
    },
    "59262207-9a6d-421c-a0c9-5d5ad5b2c465": {
      "type": "custom-liquid",
      "disabled": true,
      "settings": {
        "custom_liquid": "<style>\n    @import url('https:\/\/fonts.googleapis.com\/css2?family=Quicksand:wght@500;700&display=swap');\n* {\n\tfont-family: 'Quicksand', sans-serif;\n}\n\nbody {\n\tmargin: 0;\n\n\tdisplay: flex;\n\tjustify-content: center;\n\t\n\tbackground-color: white;\n\toverflow-x: hidden;\n}\n\n.supaviews,\n.supaview,\n.supaerror {\n\tborder-radius: 10px;\n}\n\n.supaviews {\n\tposition: relative;\n\twidth: 500px;\n\tmargin: 125px 0 50px 0;\n\tcolor: #FFFFFF;\n\tbackground-color: #1C1E20;\n\n\t&__logo {\n\t\tposition: absolute;\n\t\twidth: 200px;\n\t\tright: -55px;\n\t\ttop: -100px;\n\t\ttransition: 0.2s ease-in-out;\n\t\t\n\t\t&:hover {\n\t\t\ttransform: scale(1.1);\n\t\t}\n\t}\n\t\n\t&__gradient {\n\t\tposition: absolute;\n\t\tright: 50px;\n\t\ttop: 0;\n\t\tz-index: -1;\n\t\t\n\t\tdisplay: block;\n\t\theight: 1100px;\n\t\twidth: 1100px;\n\t\ttransform: translate(50%, -50%);\n\t\tbackground-image: radial-gradient(rgba(#6ECB90, 0.2) 15%, #16181A 60%);\n\t}\n}\n\n.supaview,\n.supaerror{ \n\tmargin: 20px;\n\tpadding: 25px;\n}\n\n.supaview {\n\tbackground-color: #24262B;\n\t\n\t&__stars {\n\t\tmargin-bottom: 15px;\n\t\tfont-size: 25px;\n\t\tcolor: #1C1E20;\n\t\t\n\t\t.checked {\n\t\t\tcolor: #6ECB90;\n\t\t\ttext-shadow: 0 0 6px #4DA76EBD;\n\t\t}\n\t}\n\t\n\t&__name {\n\t\tfont-weight: 700;\n\t\tfont-size: 20px;\n\t}\n\t\n\t&__date {\n\t\tmargin-top: 15px;\n\t\tcolor: #7D7F81;\n\t}\n\t\n\t&__rating { \n\t\tdisplay: block;\n\t\tfloat: left;\n\t\tpadding: 0;\n\t\tmargin-bottom: 15px;\n\t\tborder: none;\n\t\t\n\t\t& > input { display: none; } \n\t\t& > label:before { \n\t\t\tdisplay: inline-block;\n\t\t\tmargin-right: 5px;\n\n\t\t\tfont-family: \"Font Awesome 5 Free\";\n\t\t\tfont-size: 25px;\n\t\t\tfont-weight: 900;\n\t\t\tcontent: \"\\f005\";\n\t\t}\n\t\t\n\t\t& > label { \n\t\t\tfloat: right; \n\t\t\tcolor: #1C1E20;\n\t\t\tcursor: pointer;\n\t\t\ttransition: 0.15s ease-in-out;\n\t\t}\n\t\t\n\t\t& > input:checked ~ label,\n\t\t&:not(:checked) > label:hover,\n\t\t&:not(:checked) > label:hover ~ label { \n\t\t\tcolor: #6ECB90;\n\t\t\ttext-shadow: 0 0 6px #4DA76EBD; \n\t\t}\n\n\t\t& > input:checked + label:hover,\n\t\t& > input:checked ~ label:hover,\n\t\t& > label:hover ~ input:checked ~ label,\n\t\t& > input:checked ~ label:hover ~ label { \n\t\t\tcolor: #4DA76EBD;  \n\t\t} \n\t}\n\t\n\t&__title {\n\t\tmargin-top: 0;\n\t}\n\t\n\t&__copy {\n\t\tinput, textarea {\n\t\t\twidth: calc(100% - 20px);\n\t\t\tpadding: 10px;\n\t\t\tmargin-bottom: 10px;\n\t\t\tborder-radius: 5px;\n\t\t\tborder: 1px solid #16181A;\n\t\t\tcolor: #FFFFFF;\n\t\t\tbackground-color: transparent;\n\t\t\toutline: none;\n\t\t\t\n\t\t\t&:focus {\n\t\t\t\tborder: 1px solid #FFFFFF;\n\t\t\t}\n\t\t}\n\t}\n\t\n\t&__submit {\n\t\tpadding: 10px 15px;\n\t\tfont-weight: 700;\n\t\tcolor: #FFFFFF;\n\t\tbackground-color: #64B883;\n\t\tborder: none;\n\t\tborder-radius: 20px;\n\t\tcursor: pointer;\n\t\toutline: none;\n\t\ttransition: 0.2s ease-in-out;\n\t\t\n\t\t&:hover {\n\t\t\tbackground-color: #6ECB90;\n\t\t}\n\t}\n}\n\n.supaerror {\n\tbackground-color: #E56460;\n}\n<\/style>\n<div class=\"supaviews\">\n\t<img class=\"supaviews__logo\" src=\"https:\/\/app.supabase.io\/img\/supabase-logo.svg\"\/>\n\t<div class=\"supaviews__gradient\"><\/div>\n\t<div class=\"supaviews__add\">\n\t\t<div class=\"supaview\">\n\t\t\t<h1 class=\"supaview__title\">Add a new review<\/h1>\n\t\t\t<form id=\"review\">\n\t\t\t\t<fieldset class=\"supaview__rating\">\n\t\t\t\t\t<input type=\"radio\" id=\"star5\" name=\"rate\" value=\"5\" \/><label for=\"star5\"><\/label>\n\t\t\t\t\t<input type=\"radio\" id=\"star4\" name=\"rate\" value=\"4\" \/><label for=\"star4\"><\/label>\n\t\t\t\t\t<input type=\"radio\" id=\"star3\" name=\"rate\" value=\"3\" \/><label for=\"star3\"><\/label>\n\t\t\t\t\t<input type=\"radio\" id=\"star2\" name=\"rate\" value=\"2\" \/><label for=\"star2\"><\/label>\n\t\t\t\t\t<input type=\"radio\" id=\"star1\" name=\"rate\" value=\"1\" \/><label for=\"star1\"><\/label>\n\t\t\t\t<\/fieldset>\n\t\t\t\t<div class=\"supaview__copy\">\n\t\t\t\t\t<input type=\"text\" name=\"name\" placeholder=\"Name\"\/>\n\t\t\t\t\t<textarea name=\"message\" placeholder=\"Message\" rows=\"5\"><\/textarea>\n\t\t\t\t<\/div>\n\t\t\t\t<button class=\"supaview__submit\">Submit review<\/button>\n\t\t\t<\/form>\n\t\t<\/div>\n\t<\/div>\n\t<div class=\"supaviews__list\">\n\t\t<div class=\"supaview\">Looks empty around here..<\/div>\n\t<\/div>\n<\/div>\n<script>\n \nimport { createClient } from 'https:\/\/jspm.dev\/@supabase\/supabase-js';\n\n\nconst supaURL = '';\nconst supaKEY = '';\nconst supabase = createClient(supaURL, supaKEY);\n\n\nconst reviewsEl = document.querySelector('.supaviews__list');\n\nfunction renderError(error) {\n\tconsole.warn(error);\n\treviewsEl.innerHTML = `<div class=\"supaerror\">${error}<\/div>`;\n}\n\nfunction renderStars(rate) {\n\tlet rating = '';\n\tfor (let i = 0; i < 5; i++) {\n\t\trating += `<i class=\"fas fa-star ${i < rate ? 'checked' : ''}\"><\/i>`;\n\t}\n\treturn rating;\n}\n\nfunction renderReview(review) {\n\tconst { name, message, created } = review;\n\tconst stars = renderStars(review.rate);\n\t\n\tconst element = document.createElement(\"DIV\");\n\telement.classList.add('supaview');\n\telement.innerHTML = `\n\t\t<div class=\"supaview__stars\">${stars}<\/div>\n\t\t<div class=\"supaview__name\">${name}<\/div>\n\t\t<div class=\"supaview__message\">${message}<\/div>\n\t\t<div class=\"supaview__date\">${created}<\/div>\n\t`;\n\t\n\treturn element;\n}\n\nasync function renderReviews() {\n\t\/\/ GET all reviews\n\tconst { data: supaviews, error } = await supabase.from('supaviews').select('*');\n\t\n\tif(error) {\n\t\trenderError(`ERROR: ${error.message}`);\n\t\treturn;\n\t}\n\t\n\treviewsEl.innerHTML = '';\n\tsupaviews.forEach(supaview => {\n\t\treviewsEl.prepend(renderReview(supaview));\n\t});\n}\n\nfunction handleForm() {\n\tconst form = document.getElementById('review');\n\tconst obj = {};\n\tform.addEventListener('submit', async (e) => {\n\t\te.preventDefault();\n\t\t\n\t\tconst formData = new FormData(form);\n\t\tfor (let key of formData.keys()) {\n\t\t\tobj[key] = formData.get(key);\n\t\t}\n\t\t\n\t\t\/\/ INSERT a new review\n\t\tconst { error } = await supabase.from('supaviews').insert([obj]);\t\t\n\t\tif(error) {\n\t\t\trenderError(`ERROR: ${error.message}`);\n\t\t\treturn;\n\t\t}\n\t\t\n\t\tform.reset();\n\t\trenderReviews();\n\t});\n}\n\nrenderReviews();\nhandleForm();\n\n\t\n\n\n<\/script>",
        "full_width": false,
        "show_divider": false,
        "padding_top": 36,
        "columns_mobile": "1",
        "swipe_on_mobile": true,
        "padding_bottom": 36
      }
    },
    "d287ab75-7c33-499a-ba84-e2b6b5a156e9": {
      "type": "custom-liquid",
      "settings": {
        "custom_liquid": "<style>\n    .seacra-row {\n      display: flex;\n      flex-wrap: wrap;\n    \n\n    }\n  \n    .seacra-col {\n      flex: 1 0 15%; \/* The important bit. This percentage decides your columns.\n      The percent can be px. It just represents your minimum starting width.\n       *\/\n      \/* margin: 5px;\n       height: 300px; *\/\n      \/* color: black; *\/\n      display: flex;\n      flex-direction: column;\n      align-items: center;\n      justify-content: center;\n      font-family: \"Poppins\";\n      font-style: normal;\n      font-weight: 400;\n      font-size: 13px;\n      line-height: 24px;\n      text-align: center;\n      \n    }\n    @media screen and (max-width: 600px) {\n      .seacra-row {\n        width: 100%;\n        column-gap: 2rem;\n      }\n  \n      .seacra-col {\n         flex: 1 0 66%;\n        \n      }\n    }\n  <\/style>\n  \n  <div class=\"seacra-row slider slider--tablet\">\n    <div class=\"seacra-col\">\n      <img\n        src=\"https:\/\/cdn.shopify.com\/s\/files\/1\/0669\/6343\/9927\/files\/Frame_21_fc223f7e-ea0f-45a9-abe0-16c06cd44517.png?v=1670770279\"\n        style=\"width: 85px;\" class=\"images1\"\n      \/>\n      <p style=\"color: #cc4e61;position: relative;\n      top: 23px;font-size: 18px;\">Free & Fast<\/p>\n      <h3 style=\"font-size: 16px;color:4a4a4a; font-weight: 400;color: #4a4a4a;\">\n       Delivery Across the UK\n      <\/h3>\n    <\/div>\n    <div class=\"seacra-col\">\n      <img\n        src=\"https:\/\/cdn.shopify.com\/s\/files\/1\/0669\/6343\/9927\/files\/Frame_22_7b15ef09-dae4-4bd9-915e-df0a013d511c.png?v=1670770382\"\n        style=\"width: 78px;\" class=\"images1\"\n      \/>\n      <p style=\"color: #cc4e61;position: relative;\n      top: 23px;font-size: 18px;\">Free Returns<\/p>\n      <h3 style=\"font-size: 16px; font-weight: 400;color: #4a4a4a;\">\n        Within 30 days\n      <\/h3>\n    <\/div>\n    <div class=\"seacra-col\">\n      <img\n        src=\"https:\/\/cdn.shopify.com\/s\/files\/1\/0669\/6343\/9927\/files\/Frame_23_bfb8e0f0-ff9b-4b81-afac-0a8bb46b1c07.png?v=1670770533\"\n        style=\"width: 66px;\" class=\"images1\"\n      \/>\n      <p style=\"color: #cc4e61;position: relative;\n      top: 23px;font-size: 18px;\">97% Success<\/p>\n      <h3 style=\"font-size: 16px; font-weight: 400;color: #4a4a4a;\">\n        Rate in clinical trials\n      <\/h3>\n    <\/div>\n    <div class=\"seacra-col\">\n      <img\n        src=\"https:\/\/cdn.shopify.com\/s\/files\/1\/0669\/6343\/9927\/files\/Frame_24_7b541d30-b916-4ad6-8e43-fc2226eb6aef.png?v=1670770577\"\n        style=\"width: 65px;\"class=\"images1\"\n      \/>\n      <p style=\"color: #cc4e61;position: relative;\n      top: 23px;font-size: 18px;\">Partenered<\/p>\n      <h3 style=\"font-size: 16px; font-weight: 400;color: #4a4a4a;\">\n        With Eden Reforestation Project\n      <\/h3>\n    <\/div>\n   \n  <\/div>",
        "full_width": true,
        "show_divider": false,
        "padding_top": 36,
        "columns_mobile": "1",
        "swipe_on_mobile": true,
        "padding_bottom": 36
      }
    }
  },
  "order": [
    "main",
    "af4367ad-9bd8-42c9-a8ad-cd47dda43fe9",
    "28c9af45-1fbe-4584-a182-ef4944b481ab",
    "fbe431ed-5c35-4869-a2cb-c4c3d87dbe3e",
    "eac6855e-ae7f-4511-aeae-8e2b12d1451b",
    "1fee61a9-ef82-4918-92e3-2864e786840f",
    "33215fec-c0c5-47ba-bded-74b23046fe26",
    "85338335-2df9-4891-9265-47d749cb0dff",
    "23ad6690-908e-494d-8f26-c4eb571f6962",
    "30d21ac0-909f-4e7f-aad4-f17ae379f94c",
    "6d847e60-da1e-4358-bbd1-32444cbb490a",
    "a3a066ac-5e9b-4351-b1de-f91bea1a8c51",
    "c2c213a2-6f28-4b8e-af65-fe8235b53daa",
    "d9bb16de-fbab-4021-9002-0e6fde58c088",
    "c946058e-acd6-4195-b87e-3c0e0c963562",
    "d985bae6-46b4-4388-a1da-418c6b764aff",
    "b64310b3-30c8-48fe-8a6f-c1e08770a4cb",
    "0b5bef68-e699-4c2d-ae92-5c1914cdbaf8",
    "1df286e7-05fe-4cbb-9800-10e5d96bd8a5",
    "search",
    "4b708fd7-2e75-49e6-8353-6b28c5ab171f",
    "59262207-9a6d-421c-a0c9-5d5ad5b2c465",
    "d287ab75-7c33-499a-ba84-e2b6b5a156e9"
  ]
}
